{
  "href": "https://api.ebay.com/buy/browse/v1/item_summary/search?&limit=50&offset=0&category_ids=79720&filter=sellers%3A%7Bareatrend%7D",
  "total": 671,
  "next": "https://api.ebay.com/buy/browse/v1/item_summary/search?&limit=50&offset=50&category_ids=79720&filter=sellers%3A%7Bareatrend%7D",
  "limit": 50,
  "offset": 0,
  "itemSummaries": [
    {
      "itemId": "v1|152157088343|0",
      "title": "Oakley Men's Polarized Crosshair OO4060-06 Silver Aviator Sunglasses",
      "itemGroupHref": "https://api.ebay.com/buy/browse/v1/item_group/152157088343",
      "image": {
        "imageUrl": "http://thumbs.ebaystatic.com/images/g/id4AAOSwuzRXfM78/s-l225.jpg"
      },
      "price": {
        "value": "113.03",
        "currency": "USD"
      },
      "seller": {
        "username": "areatrend"
      },
      "marketingPrice": {
        "originalPrice": {
          "value": "200.00",
          "currency": "USD"
        },
        "discountPercentage": "43",
        "discountAmount": {
          "value": "86.97",
          "currency": "USD"
        }
      },
      "condition": "New with tags",
      "shippingOptions": [
        {
          "shippingCostType": "FIXED",
          "shippingCost": {
            "value": "0.00",
            "currency": "USD"
          }
        }
      ],
      "topRatedBuyingExperience": true,
      "buyingOptions": [
        "FIXED_PRICE"
      ],
      "itemWebUrl": "http://www.ebay.com/itm/Oakley-Mens-Polarized-Crosshair-OO4060-06-Silver-Aviator-Sunglasses-/152157088343?hash=item236d44ea57:g:id4AAOSwuzRXfM78",
      "itemLocation": {
        "country": "US"
      },
      "categories": [
        {
          "categoryId": "79720"
        },
        {
          "categoryId": "4250"
        },
        {
          "categoryId": "11450"
        },
        {
          "categoryId": "179239"
        }
      ],
      "additionalImages": [
        {
          "imageUrl": "http://galleryplus.ebayimg.com/ws/web/152157088343_2_0_1/225x225.jpg"
        },
        {
          "imageUrl": "http://galleryplus.ebayimg.com/ws/web/152157088343_3_0_1/225x225.jpg"
        }
      ]
    },
    {
      "itemId": "v1|151851655861|0",
      "title": "Oakley Men's Polarized Bottle Rocket OO9164-01 Black Wrap Sunglasses",
      "itemGroupHref": "https://api.ebay.com/buy/browse/v1/item_group/151851655861",
      "image": {
        "imageUrl": "http://thumbs.ebaystatic.com/images/g/NeYAAOSwA4dWIgkh/s-l225.jpg"
      },
      "price": {
        "value": "96.82",
        "currency": "USD"
      },
      "seller": {
        "username": "areatrend"
      },
      "marketingPrice": {
        "originalPrice": {
          "value": "160.00",
          "currency": "USD"
        },
        "discountPercentage": "39",
        "discountAmount": {
          "value": "63.18",
          "currency": "USD"
        }
      },
      "condition": "New with tags",
      "thumbnailImages": [
        {
          "imageUrl": "http://i.ebayimg.com/00/s/NjU2WDE1MDA=/z/NeYAAOSwA4dWIgkh/$_0.JPG?set_id=880000500F"
        }
      ],
      "shippingOptions": [
        {
          "shippingCostType": "FIXED",
          "shippingCost": {
            "value": "0.00",
            "currency": "USD"
          }
        }
      ],
      "topRatedBuyingExperience": true,
      "buyingOptions": [
        "FIXED_PRICE"
      ],
      "itemWebUrl": "http://www.ebay.com/itm/Oakley-Mens-Polarized-Bottle-Rocket-OO9164-01-Black-Wrap-Sunglasses-/151851655861?hash=item235b1062b5:g:NeYAAOSwA4dWIgkh",
      "itemLocation": {
        "country": "US"
      },
      "categories": [
        {
          "categoryId": "79720"
        },
        {
          "categoryId": "4250"
        },
        {
          "categoryId": "11450"
        },
        {
          "categoryId": "179239"
        }
      ]
    },
    {
      "itemId": "v1|151851655828|0",
      "title": "Oakley Men's Fives Squared OO9238-07 Brown Rectangle Sunglasses",
      "itemGroupHref": "https://api.ebay.com/buy/browse/v1/item_group/151851655828",
      "image": {
        "imageUrl": "http://thumbs.ebaystatic.com/images/g/sgIAAOSwhcJWIgkc/s-l225.jpg"
      },
      "price": {
        "value": "49.99",
        "currency": "USD"
      },
      "seller": {
        "username": "areatrend"
      },
      "marketingPrice": {
        "originalPrice": {
          "value": "90.00",
          "currency": "USD"
        },
        "discountPercentage": "44",
        "discountAmount": {
          "value": "40.01",
          "currency": "USD"
        }
      },
      "condition": "New with tags",
      "thumbnailImages": [
        {
          "imageUrl": "http://i.ebayimg.com/00/s/Njg4WDE1MDA=/z/sgIAAOSwhcJWIgkc/$_0.JPG?set_id=880000500F"
        }
      ],
      "shippingOptions": [
        {
          "shippingCostType": "FIXED",
          "shippingCost": {
            "value": "0.00",
            "currency": "USD"
          }
        }
      ],
      "topRatedBuyingExperience": true,
      "buyingOptions": [
        "FIXED_PRICE"
      ],
      "itemWebUrl": "http://www.ebay.com/itm/Oakley-Mens-Fives-Squared-OO9238-07-Brown-Rectangle-Sunglasses-/151851655828?hash=item235b106294:g:sgIAAOSwhcJWIgkc",
      "itemLocation": {
        "country": "US"
      },
      "categories": [
        {
          "categoryId": "79720"
        },
        {
          "categoryId": "4250"
        },
        {
          "categoryId": "11450"
        },
        {
          "categoryId": "179239"
        }
      ],
      "additionalImages": [{"imageUrl": "http://galleryplus.ebayimg.com/ws/web/151851655828_2_0_1/225x225.jpg"
        },
        {
          "imageUrl": "http://galleryplus.ebayimg.com/ws/web/151851655828_3_0_1/225x225.jpg"
        }
      ]
    },
    {
      "itemId": "v1|151586098390|0",
      "title": "Oakley Men's Crosshair OO4060-03 Black Square Sunglasses",
      "itemGroupHref": "https://api.ebay.com/buy/browse/v1/item_group/151586098390",
      "image": {
        "imageUrl": "http://thumbs.ebaystatic.com/images/g/4OEAAOSwf-VWYrtT/s-l225.jpg"
      },
      "price": {
        "value": "91.23",
        "currency": "USD"
      },
      "seller": {
        "username": "areatrend"
      },
      "marketingPrice": {
        "originalPrice": {
          "value": "160.00",
          "currency": "USD"
        },
        "discountPercentage": "43",
        "discountAmount": {
          "value": "68.77",
          "currency": "USD"
        }
      },
      "condition": "New with tags",
      "thumbnailImages": [
        {
          "imageUrl": "http://i.ebayimg.com/00/s/NjczWDE1MDA=/z/4OEAAOSwf-VWYrtT/$_0.JPG?set_id=880000500F"
        }
      ],
      "shippingOptions": [
        {
          "shippingCostType": "FIXED",
          "shippingCost": {
            "value": "0.00",
            "currency": "USD"
          }
        }
      ],
      "topRatedBuyingExperience": true,
      "buyingOptions": [
        "FIXED_PRICE"
      ],
      "itemWebUrl": "http://www.ebay.com/itm/Oakley-Mens-Crosshair-OO4060-03-Black-Square-Sunglasses-/151586098390?hash=item234b3c4cd6:g:4OEAAOSwf-VWYrtT",
      "itemLocation": {
        "country": "US"
      },
      "categories": [
        {
          "categoryId": "79720"
        },
        {
          "categoryId": "4250"
        },
        {
          "categoryId": "11450"
        },
        {
          "categoryId": "179239"
        }
      ],
      "additionalImages": [
        {
          "imageUrl": "http://galleryplus.ebayimg.com/ws/web/151586098390_2_0_1/225x225.jpg"
        },
        {
          "imageUrl": "http://galleryplus.ebayimg.com/ws/web/151586098390_3_0_1/225x225.jpg"
        }
      ]
    },
    {
      "itemId": "v1|141845304964|0",
      "title": "Oakley Men's Mirrored Half Jacket 2.0 OO9144-08 White Wrap Sunglasses",
      "itemGroupHref": "https://api.ebay.com/buy/browse/v1/item_group/141845304964",
      "image": {
        "imageUrl": "http://thumbs.ebaystatic.com/images/g/z3cAAOSw7FRWYrry/s-l225.jpg"
      },
      "price": {
        "value": "72.37",
        "currency": "USD"
      },
      "seller": {
        "username": "areatrend"
      },
      "marketingPrice": {
        "originalPrice": {
          "value": "120.00",
          "currency": "USD"
        },
        "discountPercentage": "40",
        "discountAmount": {
          "value": "47.63",
          "currency": "USD"
        }
      },
      "condition": "New with tags",
      "thumbnailImages": [
        {
          "imageUrl": "http://i.ebayimg.com/00/s/NTU5WDE1MDA=/z/z3cAAOSw7FRWYrry/$_0.JPG?set_id=880000500F"
        }
      ],
      "shippingOptions": [
        {
          "shippingCostType": "FIXED",
          "shippingCost": {
            "value": "0.00",
            "currency": "USD"
          }
        }
      ],
      "topRatedBuyingExperience": true,
      "buyingOptions": [
        "FIXED_PRICE"
      ],
      "itemWebUrl": "http://www.ebay.com/itm/Oakley-Mens-Mirrored-Half-Jacket-2-0-OO9144-08-White-Wrap-Sunglasses-/141845304964?hash=item2106a39684:g:z3cAAOSw7FRWYrry",
      "itemLocation": {
        "country": "US"
      },
      "categories": [
        {
          "categoryId": "79720"
        },
        {
          "categoryId": "4250"
        },
        {
          "categoryId": "11450"
        },
        {
          "categoryId": "179239"
        }
      ],
      "additionalImages": [
        {
          "imageUrl": "http://galleryplus.ebayimg.com/ws/web/141845304964_2_0_1/225x225.jpg"
        },
        {
          "imageUrl": "http://galleryplus.ebayimg.com/ws/web/141845304964_3_0_1/225x225.jpg"
        }
      ]
    },
    {
      "itemId": "v1|131554557874|0",
      "title": "Ray-Ban Men's Polarized  RB3183-002/81-63 Black Semi-Rimless Sunglasses",
      "itemGroupHref": "https://api.ebay.com/buy/browse/v1/item_group/131554557874",
      "image": {
        "imageUrl": "http://thumbs.ebaystatic.com/images/g/c-0AAOSwbdpWYrtV/s-l225.jpg"
      },
      "price": {
        "value": "89.99",
        "currency": "USD"
      },
      "seller": {
        "username": "areatrend"
      },
      "marketingPrice": {
        "originalPrice": {
          "value": "165.00",
          "currency": "USD"
        },
        "discountPercentage": "45",
        "discountAmount": {
          "value": "75.01",
          "currency": "USD"
        }
      },
      "condition": "New with tags",
      "thumbnailImages": [
        {
          "imageUrl": "http://i.ebayimg.com/00/s/NjY4WDE1MDA=/z/c-0AAOSwbdpWYrtV/$_0.JPG?set_id=880000500F"
        }
      ],
      "shippingOptions": [
        {
          "shippingCostType": "FIXED",
          "shippingCost": {
            "value": "0.00",
            "currency": "USD"
          }
        }
      ],
      "topRatedBuyingExperience": true,
      "buyingOptions": [
        "FIXED_PRICE"
      ],
      "itemWebUrl": "http://www.ebay.com/itm/Ray-Ban-Mens-Polarized-RB3183-002-81-63-Black-Semi-Rimless-Sunglasses-/131554557874?hash=item1ea1433fb2:g:c-0AAOSwbdpWYrtV",
      "itemLocation": {
        "country": "US"
      },
      "categories": [
        {
          "categoryId": "79720"
        },
        {
          "categoryId": "4250"
        },
        {
          "categoryId": "11450"
        },
        {
          "categoryId": "179239"
        }
      ],
      "additionalImages": [
        {
          "imageUrl": "http://galleryplus.ebayimg.com/ws/web/131554557874_2_0_1/225x225.jpg"
        },
        {
          "imageUrl": "http://galleryplus.ebayimg.com/ws/web/131554557874_3_0_1/225x225.jpg"
        }
      ]
    },
    {
      "itemId": "v1|131748209551|0",
      "title": "Emporio Armani Men's  EA2002-30168G-57 Gunmetal Square Sunglasses",
      "itemGroupHref": "https://api.ebay.com/buy/browse/v1/item_group/131748209551",
      "image": {
        "imageUrl": "http://thumbs.ebaystatic.com/images/g/kyYAAOSwyjBW4U4I/s-l225.jpg"
      },
      "price": {
        "value": "67.98",
        "currency": "USD"
      },
      "seller": {
        "username": "areatrend"
      },
      "marketingPrice": {
        "originalPrice": {
          "value": "145.00",
          "currency": "USD"
        },
        "discountPercentage": "53",
        "discountAmount": {
          "value": "77.02",
          "currency": "USD"
        }
      },
      "condition": "New with tags",
      "thumbnailImages": [
        {
          "imageUrl": "http://i.ebayimg.com/00/s/Nzc1WDE1MDA=/z/kyYAAOSwyjBW4U4I/$_0.JPG?set_id=880000500F"
        }
      ],
      "shippingOptions": [
        {
          "shippingCostType": "FIXED",
          "shippingCost": {
            "value": "0.00",
            "currency": "USD"
          }
        }
      ],
      "topRatedBuyingExperience": true,
      "buyingOptions": [
        "FIXED_PRICE"
      ],
      "itemWebUrl": "http://www.ebay.com/itm/Emporio-Armani-Mens-EA2002-30168G-57-Gunmetal-Square-Sunglasses-/131748209551?hash=item1eacce238f:g:kyYAAOSwyjBW4U4I",
      "itemLocation": {
        "country": "US"
      },
      "categories": [
        {
          "categoryId": "79720"
        },
        {
          "categoryId": "4250"
        },
        {
          "categoryId": "11450"
        },
        {
          "categoryId": "179239"
        }
      ],
      "additionalImages": [
        {
          "imageUrl": "http://galleryplus.ebayimg.com/ws/web/131748209551_2_0_1/225x225.jpg"
        },
        {
          "imageUrl": "http://galleryplus.ebayimg.com/ws/web/131748209551_3_0_1/225x225.jpg"
        }
      ]
    },
    {
      "itemId": "v1|152311612319|0",
      "title": "Spy Men's Polarized Caliber 673374973864 Black Rectangle Sunglasses",
      "itemGroupHref": "https://api.ebay.com/buy/browse/v1/item_group/152311612319",
      "image": {
        "imageUrl": "http://thumbs.ebaystatic.com/images/g/LHAAAOSwXeJYIwW-/s-l225.jpg"
      },
      "price": {
        "value": "68.42",
        "currency": "USD"
      },
      "seller": {
        "username": "areatrend"
      },
      "marketingPrice": {
        "originalPrice": {
          "value": "135.00",
          "currency": "USD"
        },
        "discountPercentage": "49",
        "discountAmount": {
          "value": "66.58",
          "currency": "USD"
        }
      },
      "condition": "New with tags",
      "thumbnailImages": [
        {
          "imageUrl": "http://i.ebayimg.com/00/s/NTQ1WDE1MDA=/z/LHAAAOSwXeJYIwW-/$_0.JPG?set_id=880000500F"
        }
      ],
      "shippingOptions": [
        {
          "shippingCostType": "FIXED",
          "shippingCost": {
            "value": "0.00",
            "currency": "USD"
          }
        }
      ],
      "topRatedBuyingExperience": true,
      "buyingOptions": [
        "FIXED_PRICE"
      ],
      "itemWebUrl": "http://www.ebay.com/itm/Spy-Mens-Polarized-Caliber-673374973864-Black-Rectangle-Sunglasses-/152311612319?hash=item23767ac39f:g:LHAAAOSwXeJYIwW-",
      "itemLocation": {
        "country": "US"
      },
      "categories": [
        {
          "categoryId": "79720"
        },
        {
          "categoryId": "4250"
        },
        {
          "categoryId": "11450"
        },
        {
          "categoryId": "179239"
        }
      ],
      "additionalImages": [
        {
          "imageUrl": "http://galleryplus.ebayimg.com/ws/web/152311612319_2_0_1/225x225.jpg"
        },
        {
          "imageUrl": "http://galleryplus.ebayimg.com/ws/web/152311612319_3_0_1/225x225.jpg"
        }
      ]
    },
    {
      "itemId": "v1|151841050852|0",
      "title": "Ray-Ban Men's New Wayfarer RB2132-902L-55 Tortoiseshell Wayfarer Sunglasses",
      "itemGroupHref": "https://api.ebay.com/buy/browse/v1/item_group/151841050852",
      "image": {
        "imageUrl": "http://thumbs.ebaystatic.com/images/g/IUwAAOSwf-VWWty8/s-l225.jpg"
      },
      "price": {
        "value": "92.67",
        "currency": "USD"
      },
      "seller": {
        "username": "areatrend"
      },
      "marketingPrice": {
        "originalPrice": {
          "value": "140.00",
          "currency": "USD"
        },
        "discountPercentage": "34",
        "discountAmount": {
          "value": "47.33",
          "currency": "USD"
        }
      },
      "condition": "New with tags",
      "thumbnailImages": [
        {
          "imageUrl": "http://i.ebayimg.com/00/s/NjU0WDE1MDA=/z/IUwAAOSwf-VWWty8/$_0.JPG?set_id=880000500F"
        }
      ],
      "shippingOptions": [
        {
          "shippingCostType": "FIXED",
          "shippingCost": {
            "value": "0.00",
            "currency": "USD"
          }
        }
      ],
      "topRatedBuyingExperience": true,
      "buyingOptions": [
        "FIXED_PRICE"
      ],
      "itemWebUrl": "http://www.ebay.com/itm/Ray-Ban-Mens-New-Wayfarer-RB2132-902L-55-Tortoiseshell-Wayfarer-Sunglasses-/151841050852?hash=item235a6e90e4:g:IUwAAOSwf-VWWty8",
      "itemLocation": {
        "country": "US"
      },
      "categories": [
        {
          "categoryId": "79720"
        },
        {
          "categoryId": "4250"
        },
        {
          "categoryId": "11450"
        },
        {
          "categoryId": "179239"
        }
      ]
    },
    {
      "itemId": "v1|152184566405|0",
      "title": "Ray-Ban Men's Outdoorsman RB3030-L9500-58 Black Aviator Sunglasses",
      "itemGroupHref": "https://api.ebay.com/buy/browse/v1/item_group/152184566405",
      "image": {
        "imageUrl": "http://thumbs.ebaystatic.com/images/g/XWwAAOSwZVlXmcx7/s-l225.jpg"
      },
      "price": {
        "value": "85.44",
        "currency": "USD"
      },
      "seller": {
        "username": "areatrend"
      },
      "marketingPrice": {
        "originalPrice": {
          "value": "150.00",
          "currency": "USD"
        },
        "discountPercentage": "43",
        "discountAmount": {
          "value": "64.56",
          "currency": "USD"
        }
      },
      "condition": "New with tags",
      "thumbnailImages": [
        {
          "imageUrl": "http://i.ebayimg.com/00/s/Njk2WDE1MDA=/z/XWwAAOSwZVlXmcx7/$_0.JPG?set_id=880000500F"
        }
      ],
      "shippingOptions": [
        {
          "shippingCostType": "FIXED",
          "shippingCost": {
            "value": "0.00",
            "currency": "USD"
          }
        }
      ],
      "topRatedBuyingExperience": true,
      "buyingOptions": [
        "FIXED_PRICE"
      ],
      "itemWebUrl": "http://www.ebay.com/itm/Ray-Ban-Mens-Outdoorsman-RB3030-L9500-58-Black-Aviator-Sunglasses-/152184566405?hash=item236ee83285:g:XWwAAOSwZVlXmcx7",
      "itemLocation": {
        "country": "US"
      },
      "categories": [
        {
          "categoryId": "79720"
        },
        {
          "categoryId": "4250"
        },
        {
          "categoryId": "11450"
        },
        {
          "categoryId": "179239"
        }
      ],
      "additionalImages": [
        {
          "imageUrl": "http://galleryplus.ebayimg.com/ws/web/152184566405_2_0_1/225x225.jpg"
        },
        {
          "imageUrl": "http://galleryplus.ebayimg.com/ws/web/152184566405_3_0_1/225x225.jpg"
        }
      ]
    },
    {
      "itemId": "v1|152350830657|0",
      "title": "Oakley Men's Polarized Batwolf OO9101-04 Black Shield Sunglasses",
      "itemGroupHref": "https://api.ebay.com/buy/browse/v1/item_group/152350830657",
      "image": {
        "imageUrl": "http://thumbs.ebaystatic.com/images/g/B14AAOSwcUBYS86r/s-l225.jpg"
      },
      "price": {
        "value": "106.99",
        "currency": "USD"
      },
      "seller": {
        "username": "areatrend"
      },
      "marketingPrice": {
        "originalPrice": {
          "value": "180.00",
          "currency": "USD"
        },
        "discountPercentage": "41",
        "discountAmount": {
          "value": "73.01",
          "currency": "USD"
        }
      },
      "condition": "New with tags",
      "thumbnailImages": [
        {
          "imageUrl": "http://i.ebayimg.com/00/s/NzUwWDE1MDA=/z/B14AAOSwcUBYS86r/$_0.JPG?set_id=880000500F"
        }
      ],
      "shippingOptions": [
        {
          "shippingCostType": "FIXED",
          "shippingCost": {
            "value": "0.00",
            "currency": "USD"
          }
        }
      ],
      "topRatedBuyingExperience": true,
      "buyingOptions": [
        "FIXED_PRICE"
      ],
      "itemWebUrl": "http://www.ebay.com/itm/Oakley-Mens-Polarized-Batwolf-OO9101-04-Black-Shield-Sunglasses-/152350830657?hash=item2378d13041:g:B14AAOSwcUBYS86r",
      "itemLocation": {
        "country": "US"
      },
      "categories": [
        {
          "categoryId": "79720"
        },
        {
          "categoryId": "4250"
        },
        {
          "categoryId": "11450"
        },
        {
          "categoryId": "179239"
        }
      ],
      "additionalImages": [
        {
          "imageUrl": "http://galleryplus.ebayimg.com/ws/web/152350830657_2_0_1/225x225.jpg"
        },
        {
          "imageUrl": "http://galleryplus.ebayimg.com/ws/web/152350830657_3_0_1/225x225.jpg"
        }
      ]
    },
    {
      "itemId": "v1|152164564936|0",
      "title": "Persol Men's Polarized  PO3048S-900058-55 Black Square Sunglasses",
      "itemGroupHref": "https://api.ebay.com/buy/browse/v1/item_group/152164564936",
      "image": {
        "imageUrl": "http://thumbs.ebaystatic.com/images/g/Y~cAAOSw0kNXhLqs/s-l225.jpg"
      },
      "price": {
        "value": "131.78",
        "currency": "USD"
      },
      "seller": {
        "username": "areatrend"
      },
      "marketingPrice": {
        "originalPrice": {
          "value": "255.00",
          "currency": "USD"
        },
        "discountPercentage": "48",
        "discountAmount": {
          "value": "123.22",
          "currency": "USD"
        }
      },
      "condition": "New with tags",
      "thumbnailImages": [
        {
          "imageUrl": "http://i.ebayimg.com/00/s/NTgwWDE1MDA=/z/Y~cAAOSw0kNXhLqs/$_0.JPG?set_id=880000500F"
        }
      ],
      "shippingOptions": [
        {
          "shippingCostType": "FIXED",
          "shippingCost": {
            "value": "0.00",
            "currency": "USD"
          }
        }
      ],
      "topRatedBuyingExperience": true,
      "buyingOptions": [
        "FIXED_PRICE"
      ],
      "itemWebUrl": "http://www.ebay.com/itm/Persol-Mens-Polarized-PO3048S-900058-55-Black-Square-Sunglasses-/152164564936?hash=item236db6ffc8:g:Y~cAAOSw0kNXhLqs",
      "itemLocation": {
        "country": "US"
      },
      "categories": [
        {
          "categoryId": "79720"
        },
        {
          "categoryId": "4250"
        },
        {
          "categoryId": "11450"
        },
        {
          "categoryId": "179239"
        }
      ],
      "additionalImages": [
        {
          "imageUrl": "http://galleryplus.ebayimg.com/ws/web/152164564936_2_0_1/225x225.jpg"
        },
        {
          "imageUrl": "http://galleryplus.ebayimg.com/ws/web/152164564936_3_0_1/225x225.jpg"
        }
      ]
    },
    {
      "itemId": "v1|142175678954|0",
      "title": "Oakley Men's Gradient Flak Jacket XLJ 03-915 Black Wrap Sunglasses",
      "itemGroupHref": "https://api.ebay.com/buy/browse/v1/item_group/142175678954",
      "image": {
        "imageUrl": "http://thumbs.ebaystatic.com/images/g/3~sAAOSwNRlYJFOR/s-l225.jpg"
      },
      "price": {
        "value": "117.82",
        "currency": "USD"
      },
      "seller": {
        "username": "areatrend"
      },
      "marketingPrice": {
        "originalPrice": {
          "value": "150.00",
          "currency": "USD"
        },
        "discountPercentage": "21",
        "discountAmount": {
          "value": "32.18",
          "currency": "USD"
        }
      },
      "condition": "New with tags",
      "thumbnailImages": [
        {
          "imageUrl": "http://i.ebayimg.com/00/s/NTIzWDE1MDA=/z/3~sAAOSwNRlYJFOR/$_0.JPG?set_id=880000500F"
        }
      ],
      "shippingOptions": [
        {
          "shippingCostType": "FIXED",
          "shippingCost": {
            "value": "0.00",
            "currency": "USD"
          }
        }
      ],
      "topRatedBuyingExperience": true,
      "buyingOptions": [
        "FIXED_PRICE"
      ],
      "itemWebUrl": "http://www.ebay.com/itm/Oakley-Mens-Gradient-Flak-Jacket-XLJ-03-915-Black-Wrap-Sunglasses-/142175678954?hash=item211a54b1ea:g:3~sAAOSwNRlYJFOR",
      "itemLocation": {
        "country": "US"
      },
      "categories": [
        {
          "categoryId": "79720"
        },
        {
          "categoryId": "4250"
        },
        {
          "categoryId": "11450"
        },
        {
          "categoryId": "179239"
        }
      ],
      "additionalImages": [
        {
          "imageUrl": "http://galleryplus.ebayimg.com/ws/web/142175678954_2_0_1/225x225.jpg"
        },
        {
          "imageUrl": "http://galleryplus.ebayimg.com/ws/web/142175678954_3_0_1/225x225.jpg"
        }
      ]
    },
    {
      "itemId": "v1|141766131363|0",
      "title": "Oakley Men's Half Jacket 2.0 Xl OO9154-23 White Wrap Sunglasses",
      "itemGroupHref": "https://api.ebay.com/buy/browse/v1/item_group/141766131363",
      "image": {
        "imageUrl": "http://thumbs.ebaystatic.com/images/g/5e0AAOSwv-NWYrtT/s-l225.jpg"
      },
      "price": {
        "value": "73.20",
        "currency": "USD"
      },
      "seller": {
        "username": "areatrend"
      },
      "marketingPrice": {
        "originalPrice": {
          "value": "120.00",
          "currency": "USD"
        },
        "discountPercentage": "39",
        "discountAmount": {
          "value": "46.80",
          "currency": "USD"
        }
      },
      "condition": "New with tags",
      "thumbnailImages": [
        {
          "imageUrl": "http://i.ebayimg.com/00/s/NjgxWDE1MDA=/z/5e0AAOSwv-NWYrtT/$_0.JPG?set_id=880000500F"
        }
      ],
      "shippingOptions": [
        {
          "shippingCostType": "FIXED",
          "shippingCost": {
            "value": "0.00",
            "currency": "USD"
          }
        }
      ],
      "topRatedBuyingExperience": true,
      "buyingOptions": [
        "FIXED_PRICE"
      ],
      "itemWebUrl": "http://www.ebay.com/itm/Oakley-Mens-Half-Jacket-2-0-Xl-OO9154-23-White-Wrap-Sunglasses-/141766131363?hash=item2101eb7ea3:g:5e0AAOSwv-NWYrtT",
      "itemLocation": {
        "country": "US"
      },
      "categories": [
        {
          "categoryId": "79720"
        },
        {
          "categoryId": "4250"
        },
        {
          "categoryId": "11450"
        },
        {
          "categoryId": "179239"
        }
      ],
      "additionalImages": [
        {
          "imageUrl": "http://galleryplus.ebayimg.com/ws/web/141766131363_2_0_1/225x225.jpg"
        },
        {
          "imageUrl": "http://galleryplus.ebayimg.com/ws/web/141766131363_3_0_1/225x225.jpg"
        }
      ]
    },
    {
      "itemId": "v1|131435484855|0",
      "title": "Oakley Men's Polarized Holbrook OO9102-02 Black Square Sunglasses",
      "itemGroupHref": "https://api.ebay.com/buy/browse/v1/item_group/131435484855",
      "image": {
        "imageUrl": "http://thumbs.ebaystatic.com/images/g/zQcAAOSwYHxWIgmC/s-l225.jpg"
      },
      "price": {
        "value": "96.99",
        "currency": "USD"
      },
      "seller": {
        "username": "areatrend"
      },
      "marketingPrice": {
        "originalPrice": {
          "value": "170.00",
          "currency": "USD"
        },
        "discountPercentage": "43",
        "discountAmount": {
          "value": "73.01",
          "currency": "USD"
        }
      },
      "condition": "New with tags",
      "thumbnailImages": [
        {
          "imageUrl": "http://i.ebayimg.com/00/s/NzAwWDE1MDA=/z/zQcAAOSwYHxWIgmC/$_0.JPG?set_id=880000500F"
        }
      ],
      "shippingOptions": [
        {
          "shippingCostType": "FIXED",
          "shippingCost": {
            "value": "0.00",
            "currency": "USD"
          }
        }
      ],
      "topRatedBuyingExperience": true,
      "buyingOptions": [
        "FIXED_PRICE"
      ],
      "itemWebUrl": "http://www.ebay.com/itm/Oakley-Mens-Polarized-Holbrook-OO9102-02-Black-Square-Sunglasses-/131435484855?hash=item1e9a2a56b7:g:zQcAAOSwYHxWIgmC",
      "itemLocation": {
        "country": "US"
      },
      "categories": [
        {
          "categoryId": "79720"
        },
        {
          "categoryId": "4250"
        },
        {
          "categoryId": "11450"
        },
        {
          "categoryId": "179239"
        }
      ],
      "additionalImages": [
        {
          "imageUrl": "http://galleryplus.ebayimg.com/ws/web/131435484855_2_0_1/225x225.jpg"
        },
        {
          "imageUrl": "http://galleryplus.ebayimg.com/ws/web/131435484855_3_0_1/225x225.jpg"
        }
      ]
    },
    {
      "itemId": "v1|131591034447|0",
      "title": "Ray-Ban Men's Mirrored Justin RB4165-852/88-55 Grey Square Sunglasses",
      "itemGroupHref": "https://api.ebay.com/buy/browse/v1/item_group/131591034447",
      "image": {
        "imageUrl": "http://thumbs.ebaystatic.com/images/g/NEAAAOSwwE5WXXJM/s-l225.jpg"
      },
      "price": {
        "value": "84.83",
        "currency": "USD"
      },
      "seller": {
        "username": "areatrend"
      },
      "marketingPrice": {
        "originalPrice": {
          "value": "115.00",
          "currency": "USD"
        },
        "discountPercentage": "26",
        "discountAmount": {
          "value": "30.17",
          "currency": "USD"
        }
      },
      "condition": "New with tags",
      "thumbnailImages": [
        {
          "imageUrl": "http://i.ebayimg.com/00/s/NzYyWDE1MDA=/z/NEAAAOSwwE5WXXJM/$_0.JPG?set_id=880000500F"
        }
      ],
      "shippingOptions": [
        {
          "shippingCostType": "FIXED",
          "shippingCost": {
            "value": "0.00",
            "currency": "USD"
          }
        }
      ],
      "topRatedBuyingExperience": true,
      "buyingOptions": [
        "FIXED_PRICE"
      ],
      "itemWebUrl": "http://www.ebay.com/itm/Ray-Ban-Mens-Mirrored-Justin-RB4165-852-88-55-Grey-Square-Sunglasses-/131591034447?hash=item1ea36fd64f:g:NEAAAOSwwE5WXXJM",
      "itemLocation": {
        "country": "US"
      },
      "categories": [
        {
          "categoryId": "79720"
        },
        {
          "categoryId": "4250"
        },
        {
          "categoryId": "11450"
        },
        {
          "categoryId": "179239"
        }
      ],
      "additionalImages": [
        {
          "imageUrl": "http://galleryplus.ebayimg.com/ws/web/131591034447_2_0_1/225x225.jpg"
        },
        {
          "imageUrl": "http://galleryplus.ebayimg.com/ws/web/131591034447_3_0_1/225x225.jpg"
        }
      ]
    },
    {
      "itemId": "v1|142271386190|0",
      "title": "Spy Men's Polarized Angler 673237973438 Black Rectangle Sunglasses",
      "itemGroupHref": "https://api.ebay.com/buy/browse/v1/item_group/142271386190",
      "image": {
        "imageUrl": "http://thumbs.ebaystatic.com/images/g/JV8AAOSwnHZYmhUd/s-l225.jpg"
      },
      "price": {
        "value": "76.22",
        "currency": "USD"
      },
      "seller": {
        "username": "areatrend"
      },
      "marketingPrice": {
        "originalPrice": {
          "value": "150.00",
          "currency": "USD"
        },
        "discountPercentage": "49",
        "discountAmount": {
          "value": "73.78",
          "currency": "USD"
        }
      },
      "condition": "New with tags",
      "thumbnailImages": [
        {
          "imageUrl": "http://i.ebayimg.com/00/s/Njk4WDE1MDA=/z/JV8AAOSwnHZYmhUd/$_0.JPG?set_id=880000500F"
        }
      ],
      "shippingOptions": [
        {
          "shippingCostType": "FIXED",
          "shippingCost": {
            "value": "0.00",
            "currency": "USD"
          }
        }
      ],
      "topRatedBuyingExperience": true,
      "buyingOptions": [
        "FIXED_PRICE"
      ],
      "itemWebUrl": "http://www.ebay.com/itm/Spy-Mens-Polarized-Angler-673237973438-Black-Rectangle-Sunglasses-/142271386190?hash=item212009124e:g:JV8AAOSwnHZYmhUd",
      "itemLocation": {
        "country": "US"
      },
      "categories": [
        {
          "categoryId": "79720"
        },
        {
          "categoryId": "4250"
        },
        {
          "categoryId": "11450"
        },
        {
          "categoryId": "179239"
        }
      ],
      "additionalImages": [
        {
          "imageUrl": "http://galleryplus.ebayimg.com/ws/web/142271386190_2_0_1/225x225.jpg"
        },
        {
          "imageUrl": "http://galleryplus.ebayimg.com/ws/web/142271386190_3_0_1/225x225.jpg"
        }
      ]
    },
    {
      "itemId": "v1|131433161853|0",
      "title": "Oakley Men's Polarized Half Jacket 2.0 OO9144-04 Black Wrap Sunglasses",
      "itemGroupHref": "https://api.ebay.com/buy/browse/v1/item_group/131433161853",
      "image": {
        "imageUrl": "http://thumbs.ebaystatic.com/images/g/1QkAAOSwo0JWIgmO/s-l225.jpg"
      },
      "price": {
        "value": "101.99",
        "currency": "USD"
      },
      "seller": {
        "username": "areatrend"
      },
      "marketingPrice": {
        "originalPrice": {
          "value": "180.00",
          "currency": "USD"
        },
        "discountPercentage": "43",
        "discountAmount": {
          "value": "78.01",
          "currency": "USD"
        }
      },
      "condition": "New with tags",
      "thumbnailImages": [
        {
          "imageUrl": "http://i.ebayimg.com/00/s/NjcwWDE1MDA=/z/1QkAAOSwo0JWIgmO/$_0.JPG?set_id=880000500F"
        }
      ],
      "shippingOptions": [
        {
          "shippingCostType": "FIXED",
          "shippingCost": {
            "value": "0.00",
            "currency": "USD"
          }
        }
      ],
      "topRatedBuyingExperience": true,
      "buyingOptions": [
        "FIXED_PRICE"
      ],
      "itemWebUrl": "http://www.ebay.com/itm/Oakley-Mens-Polarized-Half-Jacket-2-0-OO9144-04-Black-Wrap-Sunglasses-/131433161853?hash=item1e9a06e47d:g:1QkAAOSwo0JWIgmO",
      "itemLocation": {
        "country": "US"
      },
      "categories": [
        {
          "categoryId": "79720"
        },
        {
          "categoryId": "4250"
        },
        {
          "categoryId": "11450"
        },
        {
          "categoryId": "179239"
        }
      ]
    },
    {
      "itemId": "v1|151906091237|0",
      "title": "Oakley Men's Mirrored Holbrook OO9102-36 Black Square Sunglasses",
      "itemGroupHref": "https://api.ebay.com/buy/browse/v1/item_group/151906091237",
      "image": {
        "imageUrl": "http://thumbs.ebaystatic.com/images/g/VWsAAOSwnH1WYrr0/s-l225.jpg"
      },
      "price": {
        "value": "68.99",
        "currency": "USD"
      },
      "seller": {
        "username": "areatrend"
      },
      "marketingPrice": {
        "originalPrice": {
          "value": "130.00",
          "currency": "USD"
        },
        "discountPercentage": "47",
        "discountAmount": {
          "value": "61.01",
          "currency": "USD"
        }
      },
      "condition": "New with tags",
      "thumbnailImages": [
        {
          "imageUrl": "http://i.ebayimg.com/00/s/NjQ0WDE1MDA=/z/VWsAAOSwnH1WYrr0/$_0.JPG?set_id=880000500F"
        }
      ],
      "shippingOptions": [
        {
          "shippingCostType": "FIXED",
          "shippingCost": {
            "value": "0.00",
            "currency": "USD"
          }
        }
      ],
      "topRatedBuyingExperience": true,
      "buyingOptions": [
        "FIXED_PRICE"
      ],
      "itemWebUrl": "http://www.ebay.com/itm/Oakley-Mens-Mirrored-Holbrook-OO9102-36-Black-Square-Sunglasses-/151906091237?hash=item235e4f00e5:g:VWsAAOSwnH1WYrr0",
      "itemLocation": {
        "country": "US"
      },
      "categories": [
        {
          "categoryId": "79720"
        },
        {
          "categoryId": "4250"
        },
        {
          "categoryId": "11450"
        },
        {
          "categoryId": "179239"
        }
      ],
      "additionalImages": [
        {
          "imageUrl": "http://galleryplus.ebayimg.com/ws/web/151906091237_2_0_1/225x225.jpg"
        },
        {
          "imageUrl": "http://galleryplus.ebayimg.com/ws/web/151906091237_3_0_1/225x225.jpg"
        }
      ]
    },
    {
      "itemId": "v1|142144074831|0",
      "title": "Emporio Armani Men's Polarized  EA2018-3049T5-64 Brown Rectangle Sunglasses",
      "itemGroupHref": "https://api.ebay.com/buy/browse/v1/item_group/142144074831",
      "image": {
        "imageUrl": "http://thumbs.ebaystatic.com/images/g/GQAAAOSwh2xX-2tp/s-l225.jpg"
      },
      "price": {
        "value": "96.51",
        "currency": "USD"
      },
      "seller": {
        "username": "areatrend"
      },
      "marketingPrice": {
        "originalPrice": {
          "value": "215.00",
          "currency": "USD"
        },
        "discountPercentage": "55",
        "discountAmount": {
          "value": "118.49",
          "currency": "USD"
        }
      },
      "condition": "New with tags",
      "thumbnailImages": [
        {
          "imageUrl": "http://i.ebayimg.com/00/s/NjA1WDE1MDA=/z/GQAAAOSwh2xX-2tp/$_0.JPG?set_id=880000500F"
        }
      ],
      "shippingOptions": [
        {
          "shippingCostType": "FIXED",
          "shippingCost": {
            "value": "0.00",
            "currency": "USD"
          }
        }
      ],
      "topRatedBuyingExperience": true,
      "buyingOptions": [
        "FIXED_PRICE"
      ],
      "itemWebUrl": "http://www.ebay.com/itm/Emporio-Armani-Mens-Polarized-EA2018-3049T5-64-Brown-Rectangle-Sunglasses-/142144074831?hash=item211872744f:g:GQAAAOSwh2xX-2tp",
      "itemLocation": {
        "country": "US"
      },
      "categories": [
        {
          "categoryId": "79720"
        },
        {
          "categoryId": "4250"
        },
        {
          "categoryId": "11450"
        },
        {
          "categoryId": "179239"
        }
      ],
      "additionalImages": [
        {
          "imageUrl": "http://galleryplus.ebayimg.com/ws/web/142144074831_2_0_1/225x225.jpg"
        },
        {
          "imageUrl": "http://galleryplus.ebayimg.com/ws/web/142144074831_3_0_1/225x225.jpg"
        }
      ]
    },
    {
      "itemId": "v1|131776140252|0",
      "title": "Spy Men's Logan 670939973863 Black Wrap Sunglasses",
      "itemGroupHref": "https://api.ebay.com/buy/browse/v1/item_group/131776140252",
      "image": {
        "imageUrl": "http://thumbs.ebaystatic.com/images/g/-nMAAOSwJQdXCMfh/s-l225.jpg"
      },
      "price": {
        "value": "48.46",
        "currency": "USD"
      },
      "seller": {
        "username": "areatrend"
      },
      "marketingPrice": {
        "originalPrice": {
          "value": "85.00",
          "currency": "USD"
        },
        "discountPercentage": "43",
        "discountAmount": {
          "value": "36.54",
          "currency": "USD"
        }
      },
      "condition": "New with tags",
      "thumbnailImages": [
        {
          "imageUrl": "http://i.ebayimg.com/00/s/NjA0WDE1MDA=/z/-nMAAOSwJQdXCMfh/$_0.JPG?set_id=880000500F"
        }
      ],
      "shippingOptions": [
        {
          "shippingCostType": "FIXED",
          "shippingCost": {
            "value": "0.00",
            "currency": "USD"
          }
        }
      ],
      "topRatedBuyingExperience": true,
      "buyingOptions": [
        "FIXED_PRICE"
      ],
      "itemWebUrl": "http://www.ebay.com/itm/Spy-Mens-Logan-670939973863-Black-Wrap-Sunglasses-/131776140252?hash=item1eae7853dc:g:-nMAAOSwJQdXCMfh",
      "itemLocation": {
        "country": "US"
      },
      "categories": [
        {
          "categoryId": "79720"
        },
        {
          "categoryId": "4250"
        },
        {
          "categoryId": "11450"
        },
        {
          "categoryId": "179239"
        }
      ],
      "additionalImages": [
        {
          "imageUrl": "http://galleryplus.ebayimg.com/ws/web/131776140252_2_0_1/225x225.jpg"
        },
        {
          "imageUrl": "http://galleryplus.ebayimg.com/ws/web/131776140252_3_0_1/225x225.jpg"
        }
      ]
    },
    {
      "itemId": "v1|152074396690|0",
      "title": "Persol Men's  PO3092SM-901531-50 Tortoiseshell Round Sunglasses",
      "itemGroupHref": "https://api.ebay.com/buy/browse/v1/item_group/152074396690",
      "image": {
        "imageUrl": "http://thumbs.ebaystatic.com/images/g/1cwAAOSwiYFXJcpt/s-l225.jpg"
      },
      "price": {
        "value": "105.99",
        "currency": "USD"
      },
      "seller": {
        "username": "areatrend"
      },
      "marketingPrice": {
        "originalPrice": {
          "value": "205.00",
          "currency": "USD"
        },
        "discountPercentage": "48",
        "discountAmount": {
          "value": "99.01",
          "currency": "USD"
        }
      },
      "condition": "New with tags",
      "thumbnailImages": [
        {
          "imageUrl": "http://i.ebayimg.com/00/s/NjI0WDE1MDA=/z/1cwAAOSwiYFXJcpt/$_0.JPG?set_id=880000500F"
        }
      ],
      "shippingOptions": [
        {
          "shippingCostType": "FIXED",
          "shippingCost": {
            "value": "0.00",
            "currency": "USD"
          }
        }
      ],
      "topRatedBuyingExperience": true,
      "buyingOptions": [
        "FIXED_PRICE"
      ],
      "itemWebUrl": "http://www.ebay.com/itm/Persol-Mens-PO3092SM-901531-50-Tortoiseshell-Round-Sunglasses-/152074396690?hash=item2368572412:g:1cwAAOSwiYFXJcpt",
      "itemLocation": {
        "country": "US"
      },
      "categories": [
        {
          "categoryId": "79720"
        },
        {
          "categoryId": "4250"
        },
        {
          "categoryId": "11450"
        },
        {
          "categoryId": "179239"
        }
      ],
      "additionalImages": [
        {
          "imageUrl": "http://galleryplus.ebayimg.com/ws/web/152074396690_2_0_1/225x225.jpg"
        },
        {
          "imageUrl": "http://galleryplus.ebayimg.com/ws/web/152074396690_3_0_1/225x225.jpg"
        }
      ]
    },
    {
      "itemId": "v1|131767535176|0",
      "title": "Tom Ford Men's Snowdon FT0237-52N-50 Brown Square Sunglasses",
      "itemGroupHref": "https://api.ebay.com/buy/browse/v1/item_group/131767535176",
      "image": {
        "imageUrl": "http://thumbs.ebaystatic.com/images/g/1GUAAOSwdU1W~Om5/s-l225.jpg"
      },
      "price": {
        "value": "156.52",
        "currency": "USD"
      },
      "seller": {
        "username": "areatrend"
      },
      "marketingPrice": {
        "originalPrice": {
          "value": "415.00",
          "currency": "USD"
        },
        "discountPercentage": "62",
        "discountAmount": {
          "value": "258.48",
          "currency": "USD"
        }
      },
      "condition": "New with tags",
      "thumbnailImages": [
        {
          "imageUrl": "http://i.ebayimg.com/00/s/NTk5WDE1MDA=/z/1GUAAOSwdU1W~Om5/$_0.JPG?set_id=880000500F"
        }
      ],
      "shippingOptions": [
        {
          "shippingCostType": "FIXED",
          "shippingCost": {
            "value": "0.00",
            "currency": "USD"
          }
        }
      ],
      "topRatedBuyingExperience": true,
      "buyingOptions": [
        "FIXED_PRICE"
      ],
      "itemWebUrl": "http://www.ebay.com/itm/Tom-Ford-Mens-Snowdon-FT0237-52N-50-Brown-Square-Sunglasses-/131767535176?hash=item1eadf50648:g:1GUAAOSwdU1W~Om5",
      "itemLocation": {
        "country": "US"
      },
      "categories": [
        {
          "categoryId": "79720"
        },
        {
          "categoryId": "4250"
        },
        {
          "categoryId": "11450"
        },
        {
          "categoryId": "179239"
        }
      ],
      "additionalImages": [
        {
          "imageUrl": "http://galleryplus.ebayimg.com/ws/web/131767535176_2_0_1/225x225.jpg"
        },
        {
          "imageUrl": "http://galleryplus.ebayimg.com/ws/web/131767535176_3_0_1/225x225.jpg"
        }
      ]
    },
    {
      "itemId": "v1|142307771569|0",
      "title": "Versace Men's  VE4299-GB1/71-58 Black Oval Sunglasses",
      "itemGroupHref": "https://api.ebay.com/buy/browse/v1/item_group/142307771569",
      "image": {
        "imageUrl": "http://thumbs.ebaystatic.com/images/g/okQAAOSwSlBYwoGx/s-l225.jpg"
      },
      "price": {
        "value": "100.34",
        "currency": "USD"
      },
      "seller": {
        "username": "areatrend"
      },
      "marketingPrice": {
        "originalPrice": {
          "value": "200.00",
          "currency": "USD"
        },
        "discountPercentage": "50",
        "discountAmount": {
          "value": "99.66",
          "currency": "USD"
        }
      },
      "condition": "New with tags",
      "thumbnailImages": [
        {
          "imageUrl": "http://i.ebayimg.com/00/s/NzE0WDE1MDA=/z/okQAAOSwSlBYwoGx/$_0.JPG?set_id=880000500F"
        }
      ],
      "shippingOptions": [
        {
          "shippingCostType": "FIXED",
          "shippingCost": {
            "value": "0.00",
            "currency": "USD"
          }
        }
      ],
      "topRatedBuyingExperience": true,
      "buyingOptions": [
        "FIXED_PRICE"
      ],
      "itemWebUrl": "http://www.ebay.com/itm/Versace-Mens-VE4299-GB1-71-58-Black-Oval-Sunglasses-/142307771569?hash=item21223444b1:g:okQAAOSwSlBYwoGx",
      "itemLocation": {
        "country": "US"
      },
      "categories": [
        {
          "categoryId": "79720"
        },
        {
          "categoryId": "4250"
        },
        {
          "categoryId": "11450"
        },
        {
          "categoryId": "179239"
        }
      ],
      "additionalImages": [
        {
          "imageUrl": "http://galleryplus.ebayimg.com/ws/web/142307771569_2_0_1/225x225.jpg"
        },
        {
          "imageUrl": "http://galleryplus.ebayimg.com/ws/web/142307771569_3_0_1/225x225.jpg"
        }
      ]
    },
    {
      "itemId": "v1|152010303220|0",
      "title": "Versace Men's  VE2140-100287-40 Gold Shield Sunglasses",
      "itemGroupHref": "https://api.ebay.com/buy/browse/v1/item_group/152010303220",
      "image": {
        "imageUrl": "http://thumbs.ebaystatic.com/images/g/Q4QAAOSwoudW4UyC/s-l225.jpg"
      },
      "price": {
        "value": "97.80",
        "currency": "USD"
      },
      "seller": {
        "username": "areatrend"
      },
      "marketingPrice": {
        "originalPrice": {
          "value": "190.00",
          "currency": "USD"
        },
        "discountPercentage": "49",
        "discountAmount": {
          "value": "92.20",
          "currency": "USD"
        }
      },
      "condition": "New with tags",
      "thumbnailImages": [
        {
          "imageUrl": "http://i.ebayimg.com/00/s/NzU1WDE1MDA=/z/Q4QAAOSwoudW4UyC/$_0.JPG?set_id=880000500F"
        }
      ],
      "shippingOptions": [
        {
          "shippingCostType": "FIXED",
          "shippingCost": {
            "value": "0.00",
            "currency": "USD"
          }
        }
      ],
      "topRatedBuyingExperience": true,
      "buyingOptions": [
        "FIXED_PRICE"
      ],
      "itemWebUrl": "http://www.ebay.com/itm/Versace-Mens-VE2140-100287-40-Gold-Shield-Sunglasses-/152010303220?hash=item23648526f4:g:Q4QAAOSwoudW4UyC",
      "itemLocation": {
        "country": "US"
      },
      "categories": [
        {
          "categoryId": "79720"
        },
        {
          "categoryId": "4250"
        },
        {
          "categoryId": "11450"
        },
        {
          "categoryId": "179239"
        }
      ],
      "additionalImages": [
        {
          "imageUrl": "http://galleryplus.ebayimg.com/ws/web/152010303220_2_0_1/225x225.jpg"
        },
        {
          "imageUrl": "http://galleryplus.ebayimg.com/ws/web/152010303220_3_0_1/225x225.jpg"
        }
      ]
    },
    {
      "itemId": "v1|141589049009|0",
      "title": "Oakley Men's Holbrook OO9102-63 Black Square Sunglasses",
      "itemGroupHref": "https://api.ebay.com/buy/browse/v1/item_group/141589049009",
      "image": {
        "imageUrl": "http://thumbs.ebaystatic.com/images/g/RjYAAOSwP~tW3kwB/s-l225.jpg"
      },
      "price": {
        "value": "78.56",
        "currency": "USD"
      },
      "seller": {
        "username": "areatrend"
      },
      "marketingPrice": {
        "originalPrice": {
          "value": "130.00",
          "currency": "USD"
        },
        "discountPercentage": "40",
        "discountAmount": {
          "value": "51.44",
          "currency": "USD"
        }
      },
      "condition": "New with tags",
      "thumbnailImages": [
        {
          "imageUrl": "http://i.ebayimg.com/00/s/NzEzWDE1MDA=/z/RjYAAOSwP~tW3kwB/$_0.JPG?set_id=880000500F"
        }
      ],
      "shippingOptions": [
        {
          "shippingCostType": "FIXED",
          "shippingCost": {
            "value": "0.00",
            "currency": "USD"
          }
        }
      ],
      "topRatedBuyingExperience": true,
      "buyingOptions": [
        "FIXED_PRICE"
      ],
      "itemWebUrl": "http://www.ebay.com/itm/Oakley-Mens-Holbrook-OO9102-63-Black-Square-Sunglasses-/141589049009?hash=item20f75d6eb1:g:RjYAAOSwP~tW3kwB",
      "itemLocation": {
        "country": "US"
      },
      "categories": [
        {
          "categoryId": "79720"
        },
        {
          "categoryId": "4250"
        },
        {
          "categoryId": "11450"
        },
        {
          "categoryId": "179239"
        }
      ],
      "additionalImages": [
        {
          "imageUrl": "http://galleryplus.ebayimg.com/ws/web/141589049009_2_0_1/225x225.jpg"
        },
        {
          "imageUrl": "http://galleryplus.ebayimg.com/ws/web/141589049009_3_0_1/225x225.jpg"
        }
      ]
    },
    {
      "itemId": "v1|141564417837|0",
      "title": "Oakley Men's Polarized Jupiter OO9135-09 Black Rectangle Sunglasses",
      "itemGroupHref": "https://api.ebay.com/buy/browse/v1/item_group/141564417837",
      "image": {
        "imageUrl": "http://thumbs.ebaystatic.com/images/g/wHwAAOSwnipWUESD/s-l225.jpg"
      },
      "price": {
        "value": "107.22",
        "currency": "USD"
      },
      "seller": {
        "username": "areatrend"
      },
      "marketingPrice": {
        "originalPrice": {
          "value": "180.00",
          "currency": "USD"
        },
        "discountPercentage": "40",
        "discountAmount": {
          "value": "72.78",
          "currency": "USD"
        }
      },
      "condition": "New with tags",
      "thumbnailImages": [
        {
          "imageUrl": "http://i.ebayimg.com/00/s/NjE0WDE1MDA=/z/wHwAAOSwnipWUESD/$_0.JPG?set_id=880000500F"
        }
      ],
      "shippingOptions": [
        {
          "shippingCostType": "FIXED",
          "shippingCost": {
            "value": "0.00",
            "currency": "USD"
          }
        }
      ],
      "topRatedBuyingExperience": true,
      "buyingOptions": [
        "FIXED_PRICE"
      ],
      "itemWebUrl": "http://www.ebay.com/itm/Oakley-Mens-Polarized-Jupiter-OO9135-09-Black-Rectangle-Sunglasses-/141564417837?hash=item20f5e5972d:g:wHwAAOSwnipWUESD",
      "itemLocation": {
        "country": "US"
      },
      "categories": [
        {
          "categoryId": "79720"
        },
        {
          "categoryId": "4250"
        },
        {
          "categoryId": "11450"
        },
        {
          "categoryId": "179239"
        }
      ],
      "additionalImages": [
        {
          "imageUrl": "http://galleryplus.ebayimg.com/ws/web/141564417837_2_0_1/225x225.jpg"
        },
        {
          "imageUrl": "http://galleryplus.ebayimg.com/ws/web/141564417837_3_0_1/225x225.jpg"
        }
      ]
    },
    {
      "itemId": "v1|152336716748|0",
      "title": "Spy Men's Polarized Cooper 670195973864 Black Wrap Sunglasses",
      "itemGroupHref": "https://api.ebay.com/buy/browse/v1/item_group/152336716748",
      "image": {
        "imageUrl": "http://thumbs.ebaystatic.com/images/g/Rn8AAOSwcUBYPU8p/s-l225.jpg"
      },
      "price": {
        "value": "63.62",
        "currency": "USD"
      },
      "seller": {
        "username": "areatrend"
      },
      "marketingPrice": {
        "originalPrice": {
          "value": "150.00",
          "currency": "USD"
        },
        "discountPercentage": "58",
        "discountAmount": {
          "value": "86.38",
          "currency": "USD"
        }
      },
      "condition": "New with tags",
      "thumbnailImages": [
        {
          "imageUrl": "http://i.ebayimg.com/00/s/NTE5WDE1MDA=/z/Rn8AAOSwcUBYPU8p/$_0.JPG?set_id=880000500F"
        }
      ],
      "shippingOptions": [
        {
          "shippingCostType": "FIXED",
          "shippingCost": {
            "value": "0.00",
            "currency": "USD"
          }
        }
      ],
      "topRatedBuyingExperience": true,
      "buyingOptions": [
        "FIXED_PRICE"
      ],
      "itemWebUrl": "http://www.ebay.com/itm/Spy-Mens-Polarized-Cooper-670195973864-Black-Wrap-Sunglasses-/152336716748?hash=item2377f9d3cc:g:Rn8AAOSwcUBYPU8p",
      "itemLocation": {
        "country": "US"
      },
      "categories": [
        {
          "categoryId": "79720"
        },
        {
          "categoryId": "4250"
        },
        {
          "categoryId": "11450"
        },
        {
          "categoryId": "179239"
        }
      ],
      "additionalImages": [
        {
          "imageUrl": "http://galleryplus.ebayimg.com/ws/web/152336716748_2_0_1/225x225.jpg"
        },
        {
          "imageUrl": "http://galleryplus.ebayimg.com/ws/web/152336716748_3_0_1/225x225.jpg"
        }
      ]
    },
    {
      "itemId": "v1|131790451275|0",
      "title": "Ralph Lauren Men's Polarized  RA4096-106/T5-59 Gold Aviator Sunglasses",
      "itemGroupHref": "https://api.ebay.com/buy/browse/v1/item_group/131790451275",
      "image": {
        "imageUrl": "http://thumbs.ebaystatic.com/images/g/0nAAAOSwkEVXGz3E/s-l225.jpg"
      },
      "price": {
        "value": "78.91",
        "currency": "USD"
      },
      "seller": {
        "username": "areatrend"
      },
      "marketingPrice": {
        "originalPrice": {
          "value": "124.00",
          "currency": "USD"
        },
        "discountPercentage": "36",
        "discountAmount": {
          "value": "45.09",
          "currency": "USD"
        }
      },
      "condition": "New with tags",
      "thumbnailImages": [
        {
          "imageUrl": "http://i.ebayimg.com/00/s/NjM4WDE1MDA=/z/0nAAAOSwkEVXGz3E/$_0.JPG?set_id=880000500F"
        }
      ],
      "shippingOptions": [
        {
          "shippingCostType": "FIXED",
          "shippingCost": {
            "value": "0.00",
            "currency": "USD"
          }
        }
      ],
      "topRatedBuyingExperience": true,
      "buyingOptions": [
        "FIXED_PRICE"
      ],
      "itemWebUrl": "http://www.ebay.com/itm/Ralph-Lauren-Mens-Polarized-RA4096-106-T5-59-Gold-Aviator-Sunglasses-/131790451275?hash=item1eaf52b24b:g:0nAAAOSwkEVXGz3E",
      "itemLocation": {
        "country": "US"
      },
      "categories": [
        {
          "categoryId": "79720"
        },
        {
          "categoryId": "4250"
        },
        {
          "categoryId": "11450"
        },
        {
          "categoryId": "179239"
        }
      ],
      "additionalImages": [
        {
          "imageUrl": "http://galleryplus.ebayimg.com/ws/web/131790451275_2_0_1/225x225.jpg"
        },
        {
          "imageUrl": "http://galleryplus.ebayimg.com/ws/web/131790451275_3_0_1/225x225.jpg"
        }
      ]
    },
    {
      "itemId": "v1|151771544960|0",
      "title": "Ray-Ban Men's Gradient Active RB3386-003/8G-63 Silver Round Sunglasses",
      "itemGroupHref": "https://api.ebay.com/buy/browse/v1/item_group/151771544960",
      "image": {
        "imageUrl": "http://thumbs.ebaystatic.com/images/g/jSMAAOSw7FRWVZBK/s-l225.jpg"
      },
      "price": {
        "value": "74.99",
        "currency": "USD"
      },
      "seller": {
        "username": "areatrend"
      },
      "marketingPrice": {
        "originalPrice": {
          "value": "160.00",
          "currency": "USD"
        },
        "discountPercentage": "53",
        "discountAmount": {
          "value": "85.01",
          "currency": "USD"
        }
      },
      "condition": "New with tags",
      "thumbnailImages": [
        {
          "imageUrl": "http://i.ebayimg.com/00/s/NTk2WDE1MDA=/z/jSMAAOSw7FRWVZBK/$_0.JPG?set_id=880000500F"
        }
      ],
      "shippingOptions": [
        {
          "shippingCostType": "FIXED",
          "shippingCost": {
            "value": "0.00",
            "currency": "USD"
          }
        }
      ],
      "topRatedBuyingExperience": true,
      "buyingOptions": [
        "FIXED_PRICE"
      ],
      "itemWebUrl": "http://www.ebay.com/itm/Ray-Ban-Mens-Gradient-Active-RB3386-003-8G-63-Silver-Round-Sunglasses-/151771544960?hash=item235649fd80:g:jSMAAOSw7FRWVZBK",
      "itemLocation": {
        "country": "US"
      },
      "categories": [
        {
          "categoryId": "79720"
        },
        {
          "categoryId": "4250"
        },
        {
          "categoryId": "11450"
        },
        {
          "categoryId": "179239"
        }
      ],
      "additionalImages": [
        {
          "imageUrl": "http://galleryplus.ebayimg.com/ws/web/151771544960_2_0_1/225x225.jpg"
        },
        {
          "imageUrl": "http://galleryplus.ebayimg.com/ws/web/151771544960_3_0_1/225x225.jpg"
        }
      ]
    },
    {
      "itemId": "v1|131855630135|0",
      "title": "Ray-Ban Men's Predator 2 RB2027-W1847-62 Black Rectangle Sunglasses",
      "itemGroupHref": "https://api.ebay.com/buy/browse/v1/item_group/131855630135",
      "image": {
        "imageUrl": "http://thumbs.ebaystatic.com/images/g/4loAAOSwjXRXalXI/s-l225.jpg"
      },
      "price": {
        "value": "75.39",
        "currency": "USD"
      },
      "seller": {
        "username": "areatrend"
      },
      "marketingPrice": {
        "originalPrice": {
          "value": "125.00",
          "currency": "USD"
        },
        "discountPercentage": "40",
        "discountAmount": {
          "value": "49.61",
          "currency": "USD"
        }
      },
      "condition": "New with tags",
      "thumbnailImages": [
        {
          "imageUrl": "http://i.ebayimg.com/00/s/NjA1WDE1MDA=/z/4loAAOSwjXRXalXI/$_0.JPG?set_id=880000500F"
        }
      ],
      "shippingOptions": [
        {
          "shippingCostType": "FIXED",
          "shippingCost": {
            "value": "0.00",
            "currency": "USD"
          }
        }
      ],
      "topRatedBuyingExperience": true,
      "buyingOptions": [
        "FIXED_PRICE"
      ],
      "itemWebUrl": "http://www.ebay.com/itm/Ray-Ban-Mens-Predator-2-RB2027-W1847-62-Black-Rectangle-Sunglasses-/131855630135?hash=item1eb3353f37:g:4loAAOSwjXRXalXI",
      "itemLocation": {
        "country": "US"
      },
      "categories": [
        {
          "categoryId": "79720"
        },
        {
          "categoryId": "4250"
        },
        {
          "categoryId": "11450"
        },
        {
          "categoryId": "179239"
        }
      ],
      "additionalImages": [
        {
          "imageUrl": "http://galleryplus.ebayimg.com/ws/web/131855630135_2_0_1/225x225.jpg"
        },
        {
          "imageUrl": "http://galleryplus.ebayimg.com/ws/web/131855630135_3_0_1/225x225.jpg"
        }
      ]
    },
    {
      "itemId": "v1|142282764957|0",
      "title": "Burberry Men's  BE3077-118973-60 Gold Rectangle Sunglasses",
      "itemGroupHref": "https://api.ebay.com/buy/browse/v1/item_group/142282764957",
      "image": {
        "imageUrl": "http://thumbs.ebaystatic.com/images/g/t44AAOSwTuJYqBcO/s-l225.jpg"
      },
      "price": {
        "value": "112.57",
        "currency": "USD"
      },
      "seller": {
        "username": "areatrend"
      },
      "marketingPrice": {
        "originalPrice": {
          "value": "205.00",
          "currency": "USD"
        },
        "discountPercentage": "45",
        "discountAmount": {
          "value": "92.43",
          "currency": "USD"
        }
      },
      "condition": "New with tags",
      "thumbnailImages": [
        {
          "imageUrl": "http://i.ebayimg.com/00/s/NjEwWDE1MDA=/z/t44AAOSwTuJYqBcO/$_0.JPG?set_id=880000500F"
        }
      ],
      "shippingOptions": [
        {
          "shippingCostType": "FIXED",
          "shippingCost": {
            "value": "0.00",
            "currency": "USD"
          }
        }
      ],
      "topRatedBuyingExperience": true,
      "buyingOptions": [
        "FIXED_PRICE"
      ],
      "itemWebUrl": "http://www.ebay.com/itm/Burberry-Mens-BE3077-118973-60-Gold-Rectangle-Sunglasses-/142282764957?hash=item2120b6b29d:g:t44AAOSwTuJYqBcO",
      "itemLocation": {
        "country": "US"
      },
      "categories": [
        {
          "categoryId": "79720"
        },
        {
          "categoryId": "4250"
        },
        {
          "categoryId": "11450"
        },
        {
          "categoryId": "179239"
        }
      ],
      "additionalImages": [
        {
          "imageUrl": "http://galleryplus.ebayimg.com/ws/web/142282764957_2_0_1/225x225.jpg"
        },
        {
          "imageUrl": "http://galleryplus.ebayimg.com/ws/web/142282764957_3_0_1/225x225.jpg"
        }
      ]
    },
    {
      "itemId": "v1|151727503996|0",
      "title": "Ray-Ban Men's Gradient Aviator RB3386-001/13-63 Gold Aviator Sunglasses",
      "itemGroupHref": "https://api.ebay.com/buy/browse/v1/item_group/151727503996",
      "image": {
        "imageUrl": "http://thumbs.ebaystatic.com/images/g/6J8AAOSw8-tWYrt4/s-l225.jpg"
      },
      "price": {
        "value": "90.21",
        "currency": "USD"
      },
      "seller": {
        "username": "areatrend"
      },
      "marketingPrice": {
        "originalPrice": {
          "value": "160.00",
          "currency": "USD"
        },
        "discountPercentage": "44",
        "discountAmount": {
          "value": "69.79",
          "currency": "USD"
        }
      },
      "condition": "New with tags",
      "thumbnailImages": [
        {
          "imageUrl": "http://i.ebayimg.com/00/s/NzAyWDE1MDA=/z/6J8AAOSw8-tWYrt4/$_0.JPG?set_id=880000500F"
        }
      ],
      "shippingOptions": [
        {
          "shippingCostType": "FIXED",
          "shippingCost": {
            "value": "0.00",
            "currency": "USD"
          }
        }
      ],
      "topRatedBuyingExperience": true,
      "buyingOptions": [
        "FIXED_PRICE"
      ],
      "itemWebUrl": "http://www.ebay.com/itm/Ray-Ban-Mens-Gradient-Aviator-RB3386-001-13-63-Gold-Aviator-Sunglasses-/151727503996?hash=item2353a9fa7c:g:6J8AAOSw8-tWYrt4",
      "itemLocation": {
        "country": "US"
      },
      "categories": [
        {
          "categoryId": "79720"
        },
        {
          "categoryId": "4250"
        },
        {
          "categoryId": "11450"
        },
        {
          "categoryId": "179239"
        }
      ],
      "additionalImages": [
        {
          "imageUrl": "http://galleryplus.ebayimg.com/ws/web/151727503996_2_0_1/225x225.jpg"
        },
        {
          "imageUrl": "http://galleryplus.ebayimg.com/ws/web/151727503996_3_0_1/225x225.jpg"
        }
      ]
    },
    {
      "itemId": "v1|131668693289|0",
      "title": "Oakley Men's Polarized Bottle Rocket OO9164-05 Brown Wrap Sunglasses",
      "itemGroupHref": "https://api.ebay.com/buy/browse/v1/item_group/131668693289",
      "image": {
        "imageUrl": "http://thumbs.ebaystatic.com/images/g/45kAAOSwfZ1WYrrq/s-l225.jpg"
      },
      "price": {
        "value": "93.81",
        "currency": "USD"
      },
      "seller": {
        "username": "areatrend"
      },
      "marketingPrice": {
        "originalPrice": {
          "value": "160.00",
          "currency": "USD"
        },
        "discountPercentage": "41",
        "discountAmount": {
          "value": "66.19",
          "currency": "USD"
        }
      },
      "condition": "New with tags",
      "thumbnailImages": [
        {
          "imageUrl": "http://i.ebayimg.com/00/s/NTg0WDE1MDA=/z/45kAAOSwfZ1WYrrq/$_0.JPG?set_id=880000500F"
        }
      ],
      "shippingOptions": [
        {
          "shippingCostType": "FIXED",
          "shippingCost": {
            "value": "0.00",
            "currency": "USD"
          }
        }
      ],
      "topRatedBuyingExperience": true,
      "buyingOptions": [
        "FIXED_PRICE"
      ],
      "itemWebUrl": "http://www.ebay.com/itm/Oakley-Mens-Polarized-Bottle-Rocket-OO9164-05-Brown-Wrap-Sunglasses-/131668693289?hash=item1ea810d129:g:45kAAOSwfZ1WYrrq",
      "itemLocation": {
        "country": "US"
      },
      "categories": [
        {
          "categoryId": "79720"
        },
        {
          "categoryId": "4250"
        },
        {
          "categoryId": "11450"
        },
        {
          "categoryId": "179239"
        }
      ],
      "additionalImages": [
        {
          "imageUrl": "http://galleryplus.ebayimg.com/ws/web/131668693289_2_0_1/225x225.jpg"
        },
        {
          "imageUrl": "http://galleryplus.ebayimg.com/ws/web/131668693289_3_0_1/225x225.jpg"
        }
      ]
    },
    {
      "itemId": "v1|132034118592|0",
      "title": "Ray-Ban Men's Original Wayfarer RB2140-1187-50 Tortoiseshell Square Sunglasses",
      "itemGroupHref": "https://api.ebay.com/buy/browse/v1/item_group/132034118592",
      "image": {
        "imageUrl": "http://thumbs.ebaystatic.com/images/g/AjsAAOSwJ7RYURRN/s-l225.jpg"
      },
      "price": {
        "value": "78.18",
        "currency": "USD"
      },
      "seller": {
        "username": "areatrend"
      },
      "marketingPrice": {
        "originalPrice": {
          "value": "160.00",
          "currency": "USD"
        },
        "discountPercentage": "51",
        "discountAmount": {
          "value": "81.82",
          "currency": "USD"
        }
      },
      "condition": "New with tags",
      "thumbnailImages": [
        {
          "imageUrl": "http://i.ebayimg.com/00/s/NjMwWDE1MDA=/z/AjsAAOSwJ7RYURRN/$_0.JPG?set_id=880000500F"
        }
      ],
      "shippingOptions": [
        {
          "shippingCostType": "FIXED",
          "shippingCost": {
            "value": "0.00",
            "currency": "USD"
          }
        }
      ],
      "topRatedBuyingExperience": true,
      "buyingOptions": [
        "FIXED_PRICE"
      ],
      "itemWebUrl": "http://www.ebay.com/itm/Ray-Ban-Mens-Original-Wayfarer-RB2140-1187-50-Tortoiseshell-Square-Sunglasses-/132034118592?hash=item1ebdd8c3c0:g:AjsAAOSwJ7RYURRN",
      "itemLocation": {
        "country": "US"
      },
      "categories": [
        {
          "categoryId": "79720"
        },
        {
          "categoryId": "4250"
        },
        {
          "categoryId": "11450"
        },
        {
          "categoryId": "179239"
        }
      ],
      "additionalImages": [
        {
          "imageUrl": "http://galleryplus.ebayimg.com/ws/web/132034118592_2_0_1/225x225.jpg"
        },
        {
          "imageUrl": "http://galleryplus.ebayimg.com/ws/web/132034118592_3_0_1/225x225.jpg"
        }
      ]
    },
    {
      "itemId": "v1|142046858984|0",
      "title": "Ray-Ban Men's Polarized Predator RB2027-601/W1-62 Black Rectangle Sunglasses",
      "itemGroupHref": "https://api.ebay.com/buy/browse/v1/item_group/142046858984",
      "image": {
        "imageUrl": "http://thumbs.ebaystatic.com/images/g/sEYAAOSwzJ5XfM8B/s-l225.jpg"
      },
      "price": {
        "value": "102.53",
        "currency": "USD"
      },
      "seller": {
        "username": "areatrend"
      },
      "marketingPrice": {
        "originalPrice": {
          "value": "185.00",
          "currency": "USD"
        },
        "discountPercentage": "45",
        "discountAmount": {
          "value": "82.47",
          "currency": "USD"
        }
      },
      "condition": "New with tags",
      "shippingOptions": [
        {
          "shippingCostType": "FIXED",
          "shippingCost": {
            "value": "0.00",
            "currency": "USD"
          }
        }
      ],
      "topRatedBuyingExperience": true,
      "buyingOptions": [
        "FIXED_PRICE"
      ],
      "itemWebUrl": "http://www.ebay.com/itm/Ray-Ban-Mens-Polarized-Predator-RB2027-601-W1-62-Black-Rectangle-Sunglasses-/142046858984?hash=item2112a70ee8:g:sEYAAOSwzJ5XfM8B",
      "itemLocation": {
        "country": "US"
      },
      "categories": [
        {
          "categoryId": "79720"
        },
        {
          "categoryId": "4250"
        },
        {
          "categoryId": "11450"
        },
        {
          "categoryId": "179239"
        }
      ],
      "additionalImages": [
        {
          "imageUrl": "http://galleryplus.ebayimg.com/ws/web/142046858984_2_0_1/225x225.jpg"
        },
        {
          "imageUrl": "http://galleryplus.ebayimg.com/ws/web/142046858984_3_0_1/225x225.jpg"
        }
      ]
    },
    {
      "itemId": "v1|142162964209|0",
      "title": "Oakley Men's Radar OO9211-01 Black Wrap Sunglasses",
      "itemGroupHref": "https://api.ebay.com/buy/browse/v1/item_group/142162964209",
      "image": {
        "imageUrl": "http://thumbs.ebaystatic.com/images/g/qm0AAOSwal5YExwx/s-l225.jpg"
      },
      "price": {
        "value": "92.99",
        "currency": "USD"
      },
      "seller": {
        "username": "areatrend"
      },
      "marketingPrice": {
        "originalPrice": {
          "value": "180.00",
          "currency": "USD"
        },
        "discountPercentage": "48",
        "discountAmount": {
          "value": "87.01",
          "currency": "USD"
        }
      },
      "condition": "New with tags",
      "thumbnailImages": [
        {
          "imageUrl": "http://i.ebayimg.com/00/s/NjM4WDE1MDA=/z/qm0AAOSwal5YExwx/$_0.JPG?set_id=880000500F"
        }
      ],
      "shippingOptions": [
        {
          "shippingCostType": "FIXED",
          "shippingCost": {
            "value": "0.00",
            "currency": "USD"
          }
        }
      ],
      "topRatedBuyingExperience": true,
      "buyingOptions": [
        "FIXED_PRICE"
      ],
      "itemWebUrl": "http://www.ebay.com/itm/Oakley-Mens-Radar-OO9211-01-Black-Wrap-Sunglasses-/142162964209?hash=item211992aef1:g:qm0AAOSwal5YExwx",
      "itemLocation": {
        "country": "US"
      },
      "categories": [
        {
          "categoryId": "79720"
        },
        {
          "categoryId": "4250"
        },
        {
          "categoryId": "11450"
        },
        {
          "categoryId": "179239"
        }
      ],
      "additionalImages": [
        {
          "imageUrl": "http://galleryplus.ebayimg.com/ws/web/142162964209_2_0_1/225x225.jpg"
        },
        {
          "imageUrl": "http://galleryplus.ebayimg.com/ws/web/142162964209_3_0_1/225x225.jpg"
        }
      ]
    },
    {
      "itemId": "v1|152000085565|0",
      "title": "Ray-Ban Men's Alex RB4201-622/55-59 Black Aviator Sunglasses",
      "itemGroupHref": "https://api.ebay.com/buy/browse/v1/item_group/152000085565",
      "image": {
        "imageUrl": "http://thumbs.ebaystatic.com/images/g/~JoAAOSwezVW1Wq1/s-l225.jpg"
      },
      "price": {
        "value": "69.36",
        "currency": "USD"
      },
      "seller": {
        "username": "areatrend"
      },
      "marketingPrice": {
        "originalPrice": {
          "value": "140.00",
          "currency": "USD"
        },
        "discountPercentage": "50",
        "discountAmount": {
          "value": "70.64",
          "currency": "USD"
        }
      },
      "condition": "New with tags",
      "thumbnailImages": [
        {
          "imageUrl": "http://i.ebayimg.com/00/s/NjE1WDE1MDA=/z/~JoAAOSwezVW1Wq1/$_0.JPG?set_id=880000500F"
        }
      ],
      "shippingOptions": [
        {
          "shippingCostType": "FIXED",
          "shippingCost": {
            "value": "0.00",
            "currency": "USD"
          }
        }
      ],
      "topRatedBuyingExperience": true,
      "buyingOptions": [
        "FIXED_PRICE"
      ],
      "itemWebUrl": "http://www.ebay.com/itm/Ray-Ban-Mens-Alex-RB4201-622-55-59-Black-Aviator-Sunglasses-/152000085565?hash=item2363e93e3d:g:~JoAAOSwezVW1Wq1",
      "itemLocation": {
        "country": "US"
      },
      "categories": [
        {
          "categoryId": "79720"
        },
        {
          "categoryId": "4250"
        },
        {
          "categoryId": "11450"
        },
        {
          "categoryId": "179239"
        }
      ],
      "additionalImages": [
        {
          "imageUrl": "http://galleryplus.ebayimg.com/ws/web/152000085565_2_0_1/225x225.jpg"
        },
        {
          "imageUrl": "http://galleryplus.ebayimg.com/ws/web/152000085565_3_0_1/225x225.jpg"
        }
      ]
    },
    {
      "itemId": "v1|131869264357|0",
      "title": "Ray-Ban Men's Olympian RB3119-001-62 Gold Rectangle Sunglasses",
      "itemGroupHref": "https://api.ebay.com/buy/browse/v1/item_group/131869264357",
      "image": {
        "imageUrl": "http://thumbs.ebaystatic.com/images/g/P1sAAOSwvg9XfM78/s-l225.jpg"
      },
      "price": {
        "value": "86.39",
        "currency": "USD"
      },
      "seller": {
        "username": "areatrend"
      },
      "marketingPrice": {
        "originalPrice": {
          "value": "135.00",
          "currency": "USD"
        },
        "discountPercentage": "36",
        "discountAmount": {
          "value": "48.61",
          "currency": "USD"
        }
      },
      "condition": "New with tags",
      "thumbnailImages": [
        {
          "imageUrl": "http://i.ebayimg.com/00/s/Njc0WDE1MDA=/z/P1sAAOSwvg9XfM78/$_0.JPG?set_id=880000500F"
        }
      ],
      "shippingOptions": [
        {
          "shippingCostType": "FIXED",
          "shippingCost": {
            "value": "0.00",
            "currency": "USD"
          }
        }
      ],
      "topRatedBuyingExperience": true,
      "buyingOptions": [
        "FIXED_PRICE"
      ],
      "itemWebUrl": "http://www.ebay.com/itm/Ray-Ban-Mens-Olympian-RB3119-001-62-Gold-Rectangle-Sunglasses-/131869264357?hash=item1eb40549e5:g:P1sAAOSwvg9XfM78",
      "itemLocation": {
        "country": "US"
      },
      "categories": [
        {
          "categoryId": "79720"
        },
        {
          "categoryId": "4250"
        },
        {
          "categoryId": "11450"
        },
        {
          "categoryId": "179239"
        }
      ],
      "additionalImages": [
        {
          "imageUrl": "http://galleryplus.ebayimg.com/ws/web/131869264357_2_0_1/225x225.jpg"
        },
        {
          "imageUrl": "http://galleryplus.ebayimg.com/ws/web/131869264357_3_0_1/225x225.jpg"
        }
      ]
    },
    {
      "itemId": "v1|151869228015|0",
      "title": "Oakley Men's Fuel Cell OO9096-01 Black Rectangle Sunglasses",
      "itemGroupHref": "https://api.ebay.com/buy/browse/v1/item_group/151869228015",
      "image": {
        "imageUrl": "http://thumbs.ebaystatic.com/images/g/DdsAAOSwT5tWNIRr/s-l225.jpg"
      },
      "price": {
        "value": "57.99",
        "currency": "USD"
      },
      "seller": {
        "username": "areatrend"
      },
      "marketingPrice": {
        "originalPrice": {
          "value": "110.00",
          "currency": "USD"
        },
        "discountPercentage": "47",
        "discountAmount": {
          "value": "52.01",
          "currency": "USD"
        }
      },
      "condition": "New with tags",
      "thumbnailImages": [
        {
          "imageUrl": "http://i.ebayimg.com/00/s/NzMxWDE1MDA=/z/DdsAAOSwT5tWNIRr/$_0.JPG?set_id=880000500F"
        }
      ],
      "shippingOptions": [
        {
          "shippingCostType": "FIXED",
          "shippingCost": {
            "value": "0.00",
            "currency": "USD"
          }
        }
      ],
      "topRatedBuyingExperience": true,
      "buyingOptions": [
        "FIXED_PRICE"
      ],
      "itemWebUrl": "http://www.ebay.com/itm/Oakley-Mens-Fuel-Cell-OO9096-01-Black-Rectangle-Sunglasses-/151869228015?hash=item235c1c83ef:g:DdsAAOSwT5tWNIRr",
      "itemLocation": {
        "country": "US"
      },
      "categories": [
        {
          "categoryId": "79720"
        },
        {
          "categoryId": "4250"
        },
        {
          "categoryId": "11450"
        },
        {
          "categoryId": "179239"
        }
      ],
      "additionalImages": [
        {
          "imageUrl": "http://galleryplus.ebayimg.com/ws/web/151869228015_2_0_1/225x225.jpg"
        },
        {
          "imageUrl": "http://galleryplus.ebayimg.com/ws/web/151869228015_3_0_1/225x225.jpg"
        }
      ]
    },
    {
      "itemId": "v1|132093052696|0",
      "title": "Spy Men's Caliber 673374038863 Black Wrap Sunglasses",
      "itemGroupHref": "https://api.ebay.com/buy/browse/v1/item_group/132093052696",
      "image": {
        "imageUrl": "http://thumbs.ebaystatic.com/images/g/XOMAAOSw4CFYntxV/s-l225.jpg"
      },
      "price": {
        "value": "48.41",
        "currency": "USD"
      },
      "seller": {
        "username": "areatrend"
      },
      "marketingPrice": {
        "originalPrice": {
          "value": "85.00",
          "currency": "USD"
        },
        "discountPercentage": "43",
        "discountAmount": {
          "value": "36.59",
          "currency": "USD"
        }
      },
      "condition": "New with tags",
      "thumbnailImages": [
        {
          "imageUrl": "http://i.ebayimg.com/00/s/NTE0WDE1MDA=/z/XOMAAOSw4CFYntxV/$_0.JPG?set_id=880000500F"
        }
      ],
      "shippingOptions": [
        {
          "shippingCostType": "FIXED",
          "shippingCost": {
            "value": "0.00",
            "currency": "USD"
          }
        }
      ],
      "topRatedBuyingExperience": true,
      "buyingOptions": [
        "FIXED_PRICE"
      ],
      "itemWebUrl": "http://www.ebay.com/itm/Spy-Mens-Caliber-673374038863-Black-Wrap-Sunglasses-/132093052696?hash=item1ec15c0718:g:XOMAAOSw4CFYntxV",
      "itemLocation": {
        "country": "US"
      },
      "categories": [
        {
          "categoryId": "79720"
        },
        {
          "categoryId": "4250"
        },
        {
          "categoryId": "11450"
        },
        {
          "categoryId": "179239"
        }
      ],
      "additionalImages": [
        {
          "imageUrl": "http://galleryplus.ebayimg.com/ws/web/132093052696_2_0_1/225x225.jpg"
        },
        {
          "imageUrl": "http://galleryplus.ebayimg.com/ws/web/132093052696_3_0_1/225x225.jpg"
        }
      ]
    },
    {
      "itemId": "v1|131748209954|0",
      "title": "Burberry Men's  BE4181-300187-58 Black Square Sunglasses",
      "itemGroupHref": "https://api.ebay.com/buy/browse/v1/item_group/131748209954",
      "image": {
        "imageUrl": "http://thumbs.ebaystatic.com/images/g/qJIAAOSwh-1W4U7c/s-l225.jpg"
      },
      "price": {
        "value": "124.79",
        "currency": "USD"
      },
      "seller": {
        "username": "areatrend"
      },
      "marketingPrice": {
        "originalPrice": {
          "value": "240.00",
          "currency": "USD"
        },
        "discountPercentage": "48",
        "discountAmount": {
          "value": "115.21",
          "currency": "USD"
        }
      },
      "condition": "New with tags",
      "thumbnailImages": [
        {
          "imageUrl": "http://i.ebayimg.com/00/s/NzE4WDE1MDA=/z/qJIAAOSwh-1W4U7c/$_0.JPG?set_id=880000500F"
        }
      ],
      "shippingOptions": [
        {
          "shippingCostType": "FIXED",
          "shippingCost": {
            "value": "0.00",
            "currency": "USD"
          }
        }
      ],
      "topRatedBuyingExperience": true,
      "buyingOptions": [
        "FIXED_PRICE"
      ],
      "itemWebUrl": "http://www.ebay.com/itm/Burberry-Mens-BE4181-300187-58-Black-Square-Sunglasses-/131748209954?hash=item1eacce2522:g:qJIAAOSwh-1W4U7c",
      "itemLocation": {
        "country": "US"
      },
      "categories": [
        {
          "categoryId": "79720"
        },
        {
          "categoryId": "4250"
        },
        {
          "categoryId": "11450"
        },
        {
          "categoryId": "179239"
        }
      ],
      "additionalImages": [
        {
          "imageUrl": "http://galleryplus.ebayimg.com/ws/web/131748209954_2_0_1/225x225.jpg"
        },
        {
          "imageUrl": "http://galleryplus.ebayimg.com/ws/web/131748209954_3_0_1/225x225.jpg"
        }
      ]
    },
    {
      "itemId": "v1|141558144482|0",
      "title": "Oakley Men's Gradient Batwolf OO9101-07 Clear Shield Sunglasses",
      "itemGroupHref": "https://api.ebay.com/buy/browse/v1/item_group/141558144482",
      "image": {
        "imageUrl": "http://thumbs.ebaystatic.com/images/g/Ol0AAOSw14xWIglw/s-l225.jpg"
      },
      "price": {
        "value": "85.24",
        "currency": "USD"
      },
      "seller": {
        "username": "areatrend"
      },
      "marketingPrice": {
        "originalPrice": {
          "value": "150.00",
          "currency": "USD"
        },
        "discountPercentage": "43",
        "discountAmount": {
          "value": "64.76",
          "currency": "USD"
        }
      },
      "condition": "New with tags",
      "thumbnailImages": [
        {
          "imageUrl": "http://i.ebayimg.com/00/s/NjUxWDE1MDA=/z/Ol0AAOSw14xWIglw/$_0.JPG?set_id=880000500F"
        }
      ],
      "shippingOptions": [
        {
          "shippingCostType": "FIXED",
          "shippingCost": {
            "value": "0.00",
            "currency": "USD"
          }
        }
      ],
      "topRatedBuyingExperience": true,
      "buyingOptions": [
        "FIXED_PRICE"
      ],
      "itemWebUrl": "http://www.ebay.com/itm/Oakley-Mens-Gradient-Batwolf-OO9101-07-Clear-Shield-Sunglasses-/141558144482?hash=item20f585dde2:g:Ol0AAOSw14xWIglw",
      "itemLocation": {
        "country": "US"
      },
      "categories": [
        {
          "categoryId": "79720"
        },
        {
          "categoryId": "4250"
        },
        {
          "categoryId": "11450"
        },
        {
          "categoryId": "179239"
        }
      ],
      "additionalImages": [
        {
          "imageUrl": "http://galleryplus.ebayimg.com/ws/web/141558144482_2_0_1/225x225.jpg"
        },
        {
          "imageUrl": "http://galleryplus.ebayimg.com/ws/web/141558144482_3_0_1/225x225.jpg"
        }
      ]
    },
    {
      "itemId": "v1|152467059916|0",
      "title": "Ray-Ban Men's  RB4147-601/58-60 Black Round Sunglasses",
      "itemGroupHref": "https://api.ebay.com/buy/browse/v1/item_group/152467059916",
      "image": {
        "imageUrl": "http://thumbs.ebaystatic.com/images/g/HrkAAOSw32lYwoGo/s-l225.jpg"
      },
      "price": {
        "value": "134.00",
        "currency": "USD"
      },
      "seller": {
        "username": "areatrend"
      },
      "marketingPrice": {
        "originalPrice": {
          "value": "190.00",
          "currency": "USD"
        },
        "discountPercentage": "29",
        "discountAmount": {
          "value": "56.00",
          "currency": "USD"
        }
      },
      "condition": "New with tags",
      "thumbnailImages": [
        {
          "imageUrl": "http://i.ebayimg.com/00/s/NzI0WDE1MDA=/z/HrkAAOSw32lYwoGo/$_0.JPG?set_id=880000500F"
        }
      ],
      "shippingOptions": [
        {
          "shippingCostType": "FIXED",
          "shippingCost": {
            "value": "0.00",
            "currency": "USD"
          }
        }
      ],
      "topRatedBuyingExperience": true,
      "buyingOptions": [
        "FIXED_PRICE"
      ],
      "itemWebUrl": "http://www.ebay.com/itm/Ray-Ban-Mens-RB4147-601-58-60-Black-Round-Sunglasses-/152467059916?hash=item237fbeb4cc:g:HrkAAOSw32lYwoGo",
      "itemLocation": {
        "country": "US"
      },
      "categories": [
        {
          "categoryId": "79720"
        },
        {
          "categoryId": "4250"
        },
        {
          "categoryId": "11450"
        },
        {
          "categoryId": "179239"
        }
      ],
      "additionalImages": [
        {
          "imageUrl": "http://galleryplus.ebayimg.com/ws/web/152467059916_2_0_1/225x225.jpg"
        },
        {
          "imageUrl": "http://galleryplus.ebayimg.com/ws/web/152467059916_3_0_1/225x225.jpg"
        }
      ]
    },
    {
      "itemId": "v1|141609699225|0",
      "title": "Oakley Men's Gradient Batwolf OO9101-01 Black Shield Sunglasses",
      "itemGroupHref": "https://api.ebay.com/buy/browse/v1/item_group/141609699225",
      "image": {
        "imageUrl": "http://thumbs.ebaystatic.com/images/g/GPsAAOSw9mFWIgmE/s-l225.jpg"
      },
      "price": {
        "value": "85.24",
        "currency": "USD"
      },
      "seller": {
        "username": "areatrend"
      },
      "marketingPrice": {
        "originalPrice": {
          "value": "140.00",
          "currency": "USD"
        },
        "discountPercentage": "39",
        "discountAmount": {
          "value": "54.76",
          "currency": "USD"
        }
      },
      "condition": "New with tags",
      "thumbnailImages": [
        {
          "imageUrl": "http://i.ebayimg.com/00/s/Nzc3WDE1MDA=/z/GPsAAOSw9mFWIgmE/$_0.JPG?set_id=880000500F"
        }
      ],
      "shippingOptions": [
        {
          "shippingCostType": "FIXED",
          "shippingCost": {
            "value": "0.00",
            "currency": "USD"
          }
        }
      ],
      "topRatedBuyingExperience": true,
      "buyingOptions": [
        "FIXED_PRICE"
      ],
      "itemWebUrl": "http://www.ebay.com/itm/Oakley-Mens-Gradient-Batwolf-OO9101-01-Black-Shield-Sunglasses-/141609699225?hash=item20f8988799:g:GPsAAOSw9mFWIgmE",
      "itemLocation": {
        "country": "US"
      },
      "categories": [
        {
          "categoryId": "79720"
        },
        {
          "categoryId": "4250"
        },
        {
          "categoryId": "11450"
        },
        {
          "categoryId": "179239"
        }
      ],
      "additionalImages": [
        {
          "imageUrl": "http://galleryplus.ebayimg.com/ws/web/141609699225_2_0_1/225x225.jpg"
        },
        {
          "imageUrl": "http://galleryplus.ebayimg.com/ws/web/141609699225_3_0_1/225x225.jpg"
        }
      ]
    },
    {
      "itemId": "v1|132089432037|0",
      "title": "Tifosi Men's Mirrored Jet 0210400175 Black Semi-Rimless Sunglasses",
      "itemGroupHref": "https://api.ebay.com/buy/browse/v1/item_group/132089432037",
      "price": {
        "value": "26.01",
        "currency": "USD"
      },
      "seller": {
        "username": "areatrend"
      },
      "marketingPrice": {
        "originalPrice": {
          "value": "39.95",
          "currency": "USD"
        },
        "discountPercentage": "35",
        "discountAmount": {
          "value": "13.94",
          "currency": "USD"
        }
      },
      "condition": "New with tags",
      "shippingOptions": [
        {
          "shippingCostType": "FIXED",
          "shippingCost": {
            "value": "0.00",
            "currency": "USD"
          }
        }
      ],
      "topRatedBuyingExperience": true,
      "buyingOptions": [
        "FIXED_PRICE"
      ],
      "itemWebUrl": "http://www.ebay.com/itm/Tifosi-Mens-Mirrored-Jet-0210400175-Black-Semi-Rimless-Sunglasses-/132089432037?hash=item1ec124c7e5:i:132089432037",
      "itemLocation": {
        "country": "US"
      },
      "categories": [
        {
          "categoryId": "79720"
        },
        {
          "categoryId": "4250"
        },
        {
          "categoryId": "11450"
        },
        {
          "categoryId": "179239"
        }
      ],
      "additionalImages": [
        {
          "imageUrl": "http://galleryplus.ebayimg.com/ws/web/132089432037_2_0_1/225x225.jpg"
        },
        {
          "imageUrl": "http://galleryplus.ebayimg.com/ws/web/132089432037_3_0_1/225x225.jpg"
        }
      ]
    },
    {
      "itemId": "v1|151578763213|0",
      "title": "Oakley Men's Holbrook OO9102-01 Black Square Sunglasses",
      "itemGroupHref": "https://api.ebay.com/buy/browse/v1/item_group/151578763213",
      "image": {
        "imageUrl": "http://thumbs.ebaystatic.com/images/g/FlMAAOSwT5tWNITK/s-l225.jpg"
      },
      "price": {
        "value": "92.55",
        "currency": "USD"
      },
      "seller": {
        "username": "areatrend"
      },
      "marketingPrice": {
        "originalPrice": {
          "value": "120.00",
          "currency": "USD"
        },
        "discountPercentage": "23",
        "discountAmount": {
          "value": "27.45",
          "currency": "USD"
        }
      },
      "condition": "New with tags",
      "thumbnailImages": [
        {
          "imageUrl": "http://i.ebayimg.com/00/s/NzcwWDE1MDA=/z/FlMAAOSwT5tWNITK/$_0.JPG?set_id=880000500F"
        }
      ],
      "shippingOptions": [
        {
          "shippingCostType": "FIXED",
          "shippingCost": {
            "value": "0.00",
            "currency": "USD"
          }
        }
      ],
      "topRatedBuyingExperience": true,
      "buyingOptions": [
        "FIXED_PRICE"
      ],
      "itemWebUrl": "http://www.ebay.com/itm/Oakley-Mens-Holbrook-OO9102-01-Black-Square-Sunglasses-/151578763213?hash=item234acc5fcd:g:FlMAAOSwT5tWNITK",
      "itemLocation": {
        "country": "US"
      },
      "categories": [
        {
          "categoryId": "79720"
        },
        {
          "categoryId": "4250"
        },
        {
          "categoryId": "11450"
        },
        {
          "categoryId": "179239"
        }
      ],
      "additionalImages": [
        {
          "imageUrl": "http://galleryplus.ebayimg.com/ws/web/151578763213_2_0_1/225x225.jpg"
        },
        {
          "imageUrl": "http://galleryplus.ebayimg.com/ws/web/151578763213_3_0_1/225x225.jpg"
        }
      ]
    },
    {
      "itemId": "v1|132025932672|0",
      "title": "Persol Men's Polarized  PO3105S-95/58-51 Black Square Sunglasses",
      "itemGroupHref": "https://api.ebay.com/buy/browse/v1/item_group/132025932672",
      "image": {
        "imageUrl": "http://thumbs.ebaystatic.com/images/g/2a4AAOSw4GVYRoiM/s-l225.jpg"
      },
      "price": {
        "value": "173.28",
        "currency": "USD"
      },
      "seller": {
        "username": "areatrend"
      },
      "marketingPrice": {
        "originalPrice": {
          "value": "310.00",
          "currency": "USD"
        },
        "discountPercentage": "44",
        "discountAmount": {
          "value": "136.72",
          "currency": "USD"
        }
      },
      "condition": "New with tags",
      "thumbnailImages": [
        {
          "imageUrl": "http://i.ebayimg.com/00/s/NTk4WDE1MDA=/z/2a4AAOSw4GVYRoiM/$_0.JPG?set_id=880000500F"
        }
      ],
      "shippingOptions": [
        {
          "shippingCostType": "FIXED",
          "shippingCost": {
            "value": "0.00",
            "currency": "USD"
          }
        }
      ],
      "topRatedBuyingExperience": true,
      "buyingOptions": [
        "FIXED_PRICE"
      ],
      "itemWebUrl": "http://www.ebay.com/itm/Persol-Mens-Polarized-PO3105S-95-58-51-Black-Square-Sunglasses-/132025932672?hash=item1ebd5bdb80:g:2a4AAOSw4GVYRoiM",
      "itemLocation": {
        "country": "US"
      },
      "categories": [
        {
          "categoryId": "79720"
        },
        {
          "categoryId": "4250"
        },
        {
          "categoryId": "11450"
        },
        {
          "categoryId": "179239"
        }
      ],
      "additionalImages": [
        {
          "imageUrl": "http://galleryplus.ebayimg.com/ws/web/132025932672_2_0_1/225x225.jpg"
        },
        {
          "imageUrl": "http://galleryplus.ebayimg.com/ws/web/132025932672_3_0_1/225x225.jpg"
        }
      ]
    },
    {
      "itemId": "v1|142096077445|0",
      "title": "Persol Men's Polarized  PO3007S-900058-53 Black Round Sunglasses",
      "itemGroupHref": "https://api.ebay.com/buy/browse/v1/item_group/142096077445",
      "image": {
        "imageUrl": "http://thumbs.ebaystatic.com/images/g/M2sAAOSwMtxXvWpd/s-l225.jpg"
      },
      "price": {
        "value": "127.80",
        "currency": "USD"
      },
      "seller": {
        "username": "areatrend"
      },
      "marketingPrice": {
        "originalPrice": {
          "value": "300.00",
          "currency": "USD"
        },
        "discountPercentage": "57",
        "discountAmount": {
          "value": "172.20",
          "currency": "USD"
        }
      },
      "condition": "New with tags",
      "thumbnailImages": [
        {
          "imageUrl": "http://i.ebayimg.com/00/s/NjQ5WDE1MDA=/z/M2sAAOSwMtxXvWpd/$_0.JPG?set_id=880000500F"
        }
      ],
      "shippingOptions": [
        {
          "shippingCostType": "FIXED",
          "shippingCost": {
            "value": "0.00",
            "currency": "USD"
          }
        }
      ],
      "topRatedBuyingExperience": true,
      "buyingOptions": [
        "FIXED_PRICE"
      ],
      "itemWebUrl": "http://www.ebay.com/itm/Persol-Mens-Polarized-PO3007S-900058-53-Black-Round-Sunglasses-/142096077445?hash=item2115961285:g:M2sAAOSwMtxXvWpd",
      "itemLocation": {
        "country": "US"
      },
      "categories": [
        {
          "categoryId": "79720"
        },
        {
          "categoryId": "4250"
        },
        {
          "categoryId": "11450"
        },
        {
          "categoryId": "179239"
        }
      ],
      "additionalImages": [
        {
          "imageUrl": "http://galleryplus.ebayimg.com/ws/web/142096077445_2_0_1/225x225.jpg"
        },
        {
          "imageUrl": "http://galleryplus.ebayimg.com/ws/web/142096077445_3_0_1/225x225.jpg"
        }
      ]
    },
    {
      "itemId": "v1|142307771606|0",
      "title": "Ray-Ban Men's Outdoorsman RB3030-L0216-58 Gold Aviator Sunglasses",
      "itemGroupHref": "https://api.ebay.com/buy/browse/v1/item_group/142307771606",
      "image": {
        "imageUrl": "http://thumbs.ebaystatic.com/images/g/iIIAAOSwax5YwoGu/s-l225.jpg"
      },
      "price": {
        "value": "85.97",
        "currency": "USD"
      },
      "seller": {
        "username": "areatrend"
      },
      "marketingPrice": {
        "originalPrice": {
          "value": "150.00",
          "currency": "USD"
        },
        "discountPercentage": "43",
        "discountAmount": {
          "value": "64.03",
          "currency": "USD"
        }
      },
      "condition": "New with tags",
      "thumbnailImages": [
        {
          "imageUrl": "http://i.ebayimg.com/00/s/NzY4WDE1MDA=/z/iIIAAOSwax5YwoGu/$_0.JPG?set_id=880000500F"
        }
      ],
      "shippingOptions": [
        {
          "shippingCostType": "FIXED",
          "shippingCost": {
            "value": "0.00",
            "currency": "USD"
          }
        }
      ],
      "topRatedBuyingExperience": true,
      "buyingOptions": [
        "FIXED_PRICE"
      ],
      "itemWebUrl": "http://www.ebay.com/itm/Ray-Ban-Mens-Outdoorsman-RB3030-L0216-58-Gold-Aviator-Sunglasses-/142307771606?hash=item21223444d6:g:iIIAAOSwax5YwoGu",
      "itemLocation": {
        "country": "US"
      },
      "categories": [
        {
          "categoryId": "79720"
        },
        {
          "categoryId": "4250"
        },
        {
          "categoryId": "11450"
        },
        {
          "categoryId": "179239"
        }
      ],
      "additionalImages": [
        {
          "imageUrl": "http://galleryplus.ebayimg.com/ws/web/142307771606_2_0_1/225x225.jpg"
        },
        {
          "imageUrl": "http://galleryplus.ebayimg.com/ws/web/142307771606_3_0_1/225x225.jpg"
        }
      ]
    }
  ]
}